Workbook

Sheet Historical prices
A1: NVDA | B1: natural time order, .01 dividend per quarter removed | I1: MSFT | J1: 0.83 dividend per quarter removed
A2: Date | B2: Open | C2: High | D2: Low | E2: Close | F2: Adj Close | G2: Volume | H2: Log Return | I2: Date | J2: Open | K2: High | L2: Low | M2: Close | N2: Adj Close | O2: Volume | P2: Log Return
A3: 45622 | B3: 137.7 | C3: 139.3 | D3: 135.67 | E3: 136.92 | F3: 136.88 | G3: 190287700 | I3: 45622 | J3: 419.59 | K3: 429.04 | L3: 418.85 | M3: 427.99 | N3: 424.86 | O3: 23458900
A4: 45623 | B4: 135.01 | C4: 137.22 | D4: 131.8 | E4: 135.34 | F4: 135.3 | G4: 226370900 | H4: =LN(F4/F3) -> -0.011610094 | I4: 45623 | J4: 425.11 | K4: 427.23 | L4: 422.02 | M4: 422.99 | N4: 419.89 | O4: 18332400 | P4: =LN(N4/N3) -> -0.011766931
A5: 45625 | B5: 136.78 | C5: 139.35 | D5: 136.05 | E5: 138.25 | F5: 138.21 | G5: 141863200 | H5: =LN(F5/F4) -> 0.021279732 | I5: 45625 | J5: 420.09 | K5: 424.88 | L5: 417.8 | M5: 423.46 | N5: 420.36 | O5: 16271900 | P5: =LN(N5/N4) -> 0.0011187148
A6: 45628 | B6: 138.83 | C6: 140.45 | D6: 137.82 | E6: 138.63 | F6: 138.59 | G6: 171682800 | H6: =LN(F6/F5) -> 0.0027456665 | I6: 45628 | J6: 421.57 | K6: 433 | L6: 421.31 | M6: 430.98 | N6: 427.82 | O6: 20207200 | P6: =LN(N6/N5) -> 0.017591059
A7: 45629 | B7: 138.26 | C7: 140.54 | D7: 137.95 | E7: 140.26 | F7: 140.22 | G7: 164414000 | H7: =LN(F7/F6) -> 0.011692684 | I7: 45629 | J7: 429.84 | K7: 432.47 | L7: 427.74 | M7: 431.2 | N7: 428.04 | O7: 18302000 | P7: =LN(N7/N6) -> 0.00051410279
A8: 45630 | B8: 142 | C8: 145.79 | D8: 140.29 | E8: 145.14 | F8: 145.1 | G8: 231224300 | H8: =LN(F8/F7) -> 0.034210542 | I8: 45630 | J8: 433.03 | K8: 439.67 | L8: 432.63 | M8: 437.42 | N8: 434.22 | O8: 26009400 | P8: =LN(N8/N7) -> 0.014334669
A9: 45631 | B9: 145.11 | C9: 146.54 | D9: 143.95 | E9: 145.06 | F9: 145.03 | G9: 172621200 | H9: =LN(F9/F8) -> -0.00048254232 | I9: 45631 | J9: 437.92 | K9: 444.66 | L9: 436.17 | M9: 442.62 | N9: 439.38 | O9: 21697800 | P9: =LN(N9/N8) -> 0.011813324
A10: 45632 | B10: 144.6 | C10: 145.7 | D10: 141.31 | E10: 142.44 | F10: 142.41 | G10: 188505600 | H10: =LN(F10/F9) -> -0.018230396 | I10: 45632 | J10: 442.3 | K10: 446.1 | L10: 441.77 | M10: 443.57 | N10: 440.32 | O10: 18821000 | P10: =LN(N10/N9) -> 0.002137093
A11: 45635 | B11: 138.97 | C11: 139.95 | D11: 137.13 | E11: 138.81 | F11: 138.78 | G11: 189308600 | H11: =LN(F11/F10) -> -0.025820276 | I11: 45635 | J11: 442.6 | K11: 448.33 | L11: 440.5 | M11: 446.02 | N11: 442.75 | O11: 19144400 | P11: =LN(N11/N10) -> 0.0055035414
A12: 45636 | B12: 139.01 | C12: 141.82 | D12: 133.79 | E12: 135.07 | F12: 135.04 | G12: 210020900 | H12: =LN(F12/F11) -> -0.027318915 | I12: 45636 | J12: 444.39 | K12: 449.62 | L12: 441.6 | M12: 443.33 | N12: 440.08 | O12: 18469500 | P12: =LN(N12/N11) -> -0.0060487481
A13: 45637 | B13: 137.36 | C13: 140.17 | D13: 135.21 | E13: 139.31 | F13: 139.28 | G13: 184905200 | H13: =LN(F13/F12) -> 0.030915265 | I13: 45637 | J13: 444.05 | K13: 450.35 | L13: 444.05 | M13: 448.99 | N13: 445.7 | O13: 19200200 | P13: =LN(N13/N12) -> 0.012689551
A14: 45638 | B14: 137.08 | C14: 138.44 | D14: 135.8 | E14: 137.34 | F14: 137.31 | G14: 159211400 | H14: =LN(F14/F13) -> -0.014245152 | I14: 45638 | J14: 449.11 | K14: 456.16 | L14: 449.11 | M14: 449.56 | N14: 446.27 | O14: 20834800 | P14: =LN(N14/N13) -> 0.0012780701
A15: 45639 | B15: 138.94 | C15: 139.6 | D15: 132.54 | E15: 134.25 | F15: 134.22 | G15: 231514900 | H15: =LN(F15/F14) -> -0.022760899 | I15: 45639 | J15: 448.44 | K15: 451.43 | L15: 445.58 | M15: 447.27 | N15: 443.99 | O15: 20177800 | P15: =LN(N15/N14) -> -0.0051221104
... A252: 45986 | B252: 174.91 | C252: 178.16 | D252: 169.55 | E252: 177.82 | F252: 177.82 | G252: 319741500 | H252: =LN(F252/F251) -> -0.026252305 | I252: 45986 | J252: 474.07 | K252: 479.15 | L252: 464.89 | M252: 476.99 | N252: 476.99 | O252: 27992800 | P252: =LN(N252/N251) -> 0.0062882046

Sheet Call options
A1: Calls | D1: NVDA | M1: Calls | N1: Call | O1: MSFT
A2: In The Money | M2: In The Money
A3: Contract Name | B3: Last Trade Date (EST) | C3: Strike | D3: Last Price | E3: Bid | F3: Ask | G3: Change | H3: % Change | I3: Volume | J3: Open Interest | K3: Implied Volatility | M3: Contract Name | N3: Last Trade Date (EST) | O3: Strike | P3: Last Price | Q3: Bid | R3: Ask | S3: Change | T3: % Change | U3: Volume | V3: Open Interest | W3: Implied Volatility
A4: NVDA260515C00005000 | B4: 45909.469 | C4: 5 | D4: 163 | E4: 0 | F4: 0 | G4: 0 | H4: 0 | I4: 5 | J4: 3 | K4: 0 | M4: MSFT260515C00240000 | N4: 45980.417 | O4: 240 | P4: 259 | Q4: 0 | R4: 0 | S4: 0 | T4: 0 | U4: 1 | V4: 0 | W4: 0
A5: NVDA260515C00015000 | B5: 45975.576 | C5: 15 | D5: 174.33 | E5: 0 | F5: 0 | G5: 0 | H5: 0 | I5: 88 | J5: 0 | K5: 0 | M5: MSFT260515C00250000 | N5: 45924.46 | O5: 250 | P5: 266.5 | Q5: 277.05 | R5: 280.8 | S5: 0 | T5: 0 | U5: 4 | V5: 9 | W5: 1.483
A6: NVDA260515C00020000 | B6: 45986.427 | C6: 20 | D6: 151.54 | E6: 0 | F6: 0 | G6: 0 | H6: 0 | I6: 1 | J6: 0 | K6: 0 | M6: MSFT260515C00260000 | N6: 45979.597 | O6: 260 | P6: 238.07 | Q6: 0 | R6: 0 | S6: 0 | T6: 0 | U6: 4 | V6: 0 | W6: 0
A7: NVDA260515C00025000 | B7: 45917.396 | C7: 25 | D7: 148.93 | E7: 157.4 | F7: 160.95 | G7: 0 | H7: 0 | I7: 18 | J7: 100 | K7: 2.6118 | M7: MSFT260515C00270000 | N7: 45972.463 | O7: 270 | P7: 239.11 | Q7: 0 | R7: 0 | S7: 0 | T7: 0 | U7: - | V7: 0 | W7: 0
A8: NVDA260515C00030000 | B8: 45978.494 | C8: 30 | D8: 158.95 | E8: 0 | F8: 0 | G8: 0 | H8: 0 | I8: 9 | J8: 0 | K8: 0 | M8: MSFT260515C00300000 | N8: 45981.662 | O8: 300 | P8: 186.07 | Q8: 0 | R8: 0 | S8: 0 | T8: 0 | U8: 2 | V8: 0 | W8: 0
A9: NVDA260515C00040000 | B9: 45863.565 | C9: 40 | D9: 135.2 | E9: 138.45 | F9: 140.4 | G9: 0 | H9: 0 | I9: 63 | J9: 63 | K9: 1.3474 | M9: MSFT260515C00320000 | N9: 45916.575 | O9: 320 | P9: 203.29 | Q9: 200.4 | R9: 204.25 | S9: 0 | T9: 0 | U9: 1 | V9: 1 | W9: 1.0047
A10: NVDA260515C00050000 | B10: 45986.417 | C10: 50 | D10: 122.9 | E10: 0 | F10: 0 | G10: 0 | H10: 0 | I10: 1 | J10: 0 | K10: 0 | M10: MSFT260515C00330000 | N10: 45964.471 | O10: 330 | P10: 197 | Q10: 0 | R10: 0 | S10: 0 | T10: 0 | U10: 1 | V10: 0 | W10: 0
A11: NVDA260515C00055000 | B11: 45980.59 | C11: 55 | D11: 131.72 | E11: 0 | F11: 0 | G11: 0 | H11: 0 | I11: 1 | J11: 0 | K11: 0 | M11: MSFT260515C00340000 | N11: 45874.634 | O11: 340 | P11: 200.9 | Q11: 180.7 | R11: 182.9 | S11: 0 | T11: 0 | U11: 4 | V11: 4 | W11: 0.9059
A12: NVDA260515C00060000 | B12: 45979.659 | C12: 60 | D12: 124.53 | E12: 0 | F12: 0 | G12: 0 | H12: 0 | I12: 1 | J12: 0 | K12: 0 | M12: MSFT260515C00350000 | N12: 45986.658 | O12: 350 | P12: 138.8 | Q12: 0 | R12: 0 | S12: 0 | T12: 0 | U12: 6 | V12: 0 | W12: 0
A13: NVDA260515C00065000 | B13: 45981.636 | C13: 65 | D13: 119.75 | E13: 0 | F13: 0 | G13: 0 | H13: 0 | I13: 1 | J13: 0 | K13: 0 | M13: MSFT260515C00360000 | N13: 45980.508 | O13: 360 | P13: 137.93 | Q13: 0 | R13: 0 | S13: 0 | T13: 0 | U13: 1 | V13: 0 | W13: 0
A14: NVDA260515C00070000 | B14: 45966.588 | C14: 70 | D14: 133.87 | E14: 0 | F14: 0 | G14: 0 | H14: 0 | I14: 5 | J14: 0 | K14: 0 | M14: MSFT260515C00370000 | N14: 45974.576 | O14: 370 | P14: 146.9 | Q14: 0 | R14: 0 | S14: 0 | T14: 0 | U14: 1 | V14: 0 | W14: 0
A15: NVDA260515C00075000 | B15: 45982.447 | C15: 75 | D15: 102.63 | E15: 0 | F15: 0 | G15: 0 | H15: 0 | I15: 5 | J15: 0 | K15: 0 | M15: MSFT260515C00380000 | N15: 45982.598 | O15: 380 | P15: 111.86 | Q15: 0 | R15: 0 | S15: 0 | T15: 0 | U15: 1 | V15: 0 | W15: 0
A16: NVDA260515C00080000 | B16: 45982.51 | C16: 80 | D16: 103.01 | E16: 0 | F16: 0 | G16: 0 | H16: 0 | I16: 8 | J16: 0 | K16: 0 | M16: MSFT260515C00390000 | N16: 45986.421 | O16: 390 | P16: 94.5 | Q16: 0 | R16: 0 | S16: 0 | T16: 0 | U16: 1 | V16: 0 | W16: 0
A17: NVDA260515C00085000 | B17: 45982.403 | C17: 85 | D17: 95 | E17: 0 | F17: 0 | G17: 0 | H17: 0 | I17: 2 | J17: 0 | K17: 0 | M17: MSFT260515C00400000 | N17: 45986.649 | O17: 400 | P17: 95 | Q17: 0 | R17: 0 | S17: 0 | T17: 0 | U17: 6 | V17: 0 | W17: 0
A18: NVDA260515C00090000 | B18: 45986.66 | C18: 90 | D18: 90.78 | E18: 0 | F18: 0 | G18: 0 | H18: 0 | I18: 3 | J18: 0 | K18: 0 | M18: MSFT260515C00410000 | N18: 45986.415 | O18: 410 | P18: 80.2 | Q18: 0 | R18: 0 | S18: 0 | T18: 0 | U18: 8 | V18: 0 | W18: 0
A19: NVDA260515C00095000 | B19: 45981.483 | C19: 95 | D19: 96.5 | E19: 0 | F19: 0 | G19: 0 | H19: 0 | I19: 2 | J19: 0 | K19: 0 | M19: MSFT260515C00420000 | N19: 45986.583 | O19: 420 | P19: 78.33 | Q19: 0 | R19: 0 | S19: 0 | T19: 0 | U19: 20 | V19: 0 | W19: 0
... A50: NVDA260515C00300000 | B50: 45986.653 | C50: 300 | D50: 1.65 | E50: 0 | F50: 0 | G50: 0 | H50: 0 | I50: 109 | J50: 0 | K50: 0.125 | M50: MSFT260515C00800000 | N50: 45985.396 | O50: 800 | P50: 0.1 | Q50: 0 | R50: 0 | S50: 0 | T50: 0 | U50: 8 | V50: 0 | W50: 0.125
A51: NVDA260515C00310000 | B51: 45986.628 | C51: 310 | D51: 1.3 | E51: 0 | F51: 0 | G51: 0 | H51: 0 | I51: 15 | J51: 0 | K51: 0.125
A52: NVDA260515C00320000 | B52: 45986.631 | C52: 320 | D52: 1.13 | E52: 0 | F52: 0 | G52: 0 | H52: 0 | I52: 291 | J52: 0 | K52: 0.125
A53: NVDA260515C00330000 | B53: 45986.661 | C53: 330 | D53: 0.99 | E53: 0 | F53: 0 | G53: 0 | H53: 0 | I53: 213 | J53: 0 | K53: 0.125
A54: NVDA260515C00340000 | B54: 45986.666 | C54: 340 | D54: 0.86 | E54: 0 | F54: 0 | G54: 0 | H54: 0 | I54: 16 | J54: 0 | K54: 0.25
A55: NVDA260515C00350000 | B55: 45986.633 | C55: 350 | D55: 0.71 | E55: 0 | F55: 0 | G55: 0 | H55: 0 | I55: 30 | J55: 0 | K55: 0.25
A56: NVDA260515C00360000 | B56: 45986.662 | C56: 360 | D56: 0.62 | E56: 0 | F56: 0 | G56: 0 | H56: 0 | I56: 15 | J56: 0 | K56: 0.25
A57: NVDA260515C00370000 | B57: 45986.593 | C57: 370 | D57: 0.47 | E57: 0 | F57: 0 | G57: 0 | H57: 0 | I57: 51 | J57: 0 | K57: 0.25
A58: NVDA260515C00380000 | B58: 45986.419 | C58: 380 | D58: 0.33 | E58: 0 | F58: 0 | G58: 0 | H58: 0 | I58: 8 | J58: 0 | K58: 0.25
A59: NVDA260515C00390000 | B59: 45986.627 | C59: 390 | D59: 0.37 | E59: 0 | F59: 0 | G59: 0 | H59: 0 | I59: 3 | J59: 0 | K59: 0.25
A60: NVDA260515C00400000 | B60: 45986.643 | C60: 400 | D60: 0.33 | E60: 0 | F60: 0 | G60: 0 | H60: 0 | I60: 47 | J60: 0 | K60: 0.25
A61: NVDA260515C00410000 | B61: 45985.438 | C61: 410 | D61: 0.26 | E61: 0 | F61: 0 | G61: 0 | H61: 0 | I61: 4 | J61: 0 | K61: 0.25
A62: NVDA260515C00420000 | B62: 45986.647 | C62: 420 | D62: 0.27 | E62: 0 | F62: 0 | G62: 0 | H62: 0 | I62: 206 | J62: 0 | K62: 0.25

Sheet Basket Options
B3: Parameter | C3: Value
B4: Valuation Date | C4: 11-25-2025 | L4: BSM Simulation | O4: Correlation | Q4: Price at Exp | AA4: Shares | AC4: Options
B5: Option Expiration | C5: 05-15-2026 | G5: Call Prices | M5: z1 | N5: z2 | O5: z1 | P5: z2 | Q5: NVDA | R5: MSFT | S5: Basket | T5: Basket Call | U5: Hedge Value | AA5: NVDA | AB5: MSFT | AC5: NVDA | AD5: MSFT | AE5: Residual
B6: Risk-Free Rate | C6: 0.0377 | G6: NVDA | I6: MSFT | L6: 1 | M6: =_xlfn.NORM.S.INV(RAND()) -> 1.4776522 | N6: =_xlfn.NORM.S.INV(RAND()) -> -1.2139452 | O6: =M6 -> 1.4776522 | P6: =($D$16 * M6) + (SQRT(1 - $D$16^2) * N6) -> -0.01852967 | Q6: =$C$12*EXP(($C$6-$C$15-0.5*$C$13^2)*$C$8+$C$13*SQRT($C$8)*O6) -> 282.06245 | R6: =$D$12*EXP(($C$6-$D$15-0.5*$D$13^2)*$C$8+$D$13*SQRT($C$8)*P6) -> 474.89584 | S6: =SUMPRODUCT(Q6:R6,$C$19:$D$19) -> 12908890 | T6: =MAX(S6-$C$7,0) -> 2908890.1 | U6: =T6-AE6 -> 2927207 | AA6: =Q6 -> 282.06245 | AB6: =R6 -> 474.89584 | AC6: =MAX(AA6-$X$10,0) -> 107.06245 | AD6: =MAX(AB6-$Y$10,0) -> 0 | AE6: =T6-$AL$7-SUMPRODUCT($AH$17:$AK$17,AA6:AD6) -> -18316.883 | AH6: LINEST
B7: Total Notional | C7: 10000000 | G7: Strike | H7: Price | I7: Strike | J7: Price | L7: 2 | M7: =_xlfn.NORM.S.INV(RAND()) -> -0.35570054 | N7: =_xlfn.NORM.S.INV(RAND()) -> -0.19131799 | O7: =M7 -> -0.35570054 | P7: =($D$16 * M7) + (SQRT(1 - $D$16^2) * N7) -> -0.37211959 | Q7: =$C$12*EXP(($C$6-$C$15-0.5*$C$13^2)*$C$8+$C$13*SQRT($C$8)*O7) -> 150.31207 | R7: =$D$12*EXP(($C$6-$D$15-0.5*$D$13^2)*$C$8+$D$13*SQRT($C$8)*P7) -> 447.90163 | S7: =SUMPRODUCT(Q7:R7,$C$19:$D$19) -> 8921379.6 | T7: =MAX(S7-$C$7,0) -> 0 | U7: =T7-AE7 -> -115780.42 | AA7: =Q7 -> 150.31207 | AB7: =R7 -> 447.90163 | AC7: =MAX(AA7-$X$10,0) -> 0 | AD7: =MAX(AB7-$Y$10,0) -> 0 | AE7: =T7-$AL$7-SUMPRODUCT($AH$17:$AK$17,AA7:AD7) -> 115780.42 | AH7: {=LINEST(T6:T10005,AA6:AD10005,TRUE,TRUE)} -> 10433.808 | AI7: 29856.568 | AJ7: -231.75765 | AK7: -1117.8244 | AL7: 156046.7
B8: t | C8: 0.47 | G8: ='Call options'!C4 -> 5 | H8: ='Call options'!D4 -> 163 | I8: ='Call options'!O4 -> 240 | J8: ='Call options'!P4 -> 259 | L8: 3 | M8: =_xlfn.NORM.S.INV(RAND()) -> 0.81361628 | N8: =_xlfn.NORM.S.INV(RAND()) -> 0.28740234 | O8: =M8 -> 0.81361628 | P8: =($D$16 * M8) + (SQRT(1 - $D$16^2) * N8) -> 0.73418803 | Q8: =$C$12*EXP(($C$6-$C$15-0.5*$C$13^2)*$C$8+$C$13*SQRT($C$8)*O8) -> 224.56292 | R8: =$D$12*EXP(($C$6-$D$15-0.5*$D$13^2)*$C$8+$D$13*SQRT($C$8)*P8) -> 537.90184 | S8: =SUMPRODUCT(Q8:R8,$C$19:$D$19) -> 11952547 | T8: =MAX(S8-$C$7,0) -> 1952547.2 | U8: =T8-AE8 -> 1864277.3 | X8: NVDA | Y8: MSFT | AA8: =Q8 -> 224.56292 | AB8: =R8 -> 537.90184 | AC8: =MAX(AA8-$X$10,0) -> 49.562918 | AD8: =MAX(AB8-$Y$10,0) -> 57.901843 | AE8: =T8-$AL$7-SUMPRODUCT($AH$17:$AK$17,AA8:AD8) -> 88269.923 | AH8: 87.576115 | AI8: 117.95536 | AJ8: 60.541673 | AK8: 88.918523 | AL8: 23603.61
B9: Exp(-rt) | C9: =EXP(-C6*C8) -> 0.98243706 | G9: ='Call options'!C5 -> 15 | H9: ='Call options'!D5 -> 174.33 | I9: ='Call options'!O5 -> 250 | J9: ='Call options'!P5 -> 266.5 | L9: 4 | M9: =_xlfn.NORM.S.INV(RAND()) -> 1.4627865 | N9: =_xlfn.NORM.S.INV(RAND()) -> -1.3587383 | O9: =M9 -> 1.4627865 | P9: =($D$16 * M9) + (SQRT(1 - $D$16^2) * N9) -> -0.14061935 | Q9: =$C$12*EXP(($C$6-$C$15-0.5*$C$13^2)*$C$8+$C$13*SQRT($C$8)*O9) -> 280.62658 | R9: =$D$12*EXP(($C$6-$D$15-0.5*$D$13^2)*$C$8+$D$13*SQRT($C$8)*P9) -> 465.39602 | S9: =SUMPRODUCT(Q9:R9,$C$19:$D$19) -> 12768939 | T9: =MAX(S9-$C$7,0) -> 2768939.3 | U9: =T9-AE9 -> 2888143.6 | W9: Market | X9: 177 | Y9: 476 | AA9: =Q9 -> 280.62658 | AB9: =R9 -> 465.39602 | AC9: =MAX(AA9-$X$10,0) -> 105.62658 | AD9: =MAX(AB9-$Y$10,0) -> 0 | AE9: =T9-$AL$7-SUMPRODUCT($AH$17:$AK$17,AA9:AD9) -> -119204.3 | AH9: 0.98600863 | AI9: 192993.7 | AJ9: #N/A | AK9: #N/A | AL9: #N/A
G10: ='Call options'!C6 -> 20 | H10: ='Call options'!D6 -> 151.54 | I10: ='Call options'!O6 -> 260 | J10: ='Call options'!P6 -> 238.07 | L10: 5 | M10: =_xlfn.NORM.S.INV(RAND()) -> 0.51865303 | N10: =_xlfn.NORM.S.INV(RAND()) -> -0.93195212 | O10: =M10 -> 0.51865303 | P10: =($D$16 * M10) + (SQRT(1 - $D$16^2) * N10) -> -0.40046736 | Q10: =$C$12*EXP(($C$6-$C$15-0.5*$C$13^2)*$C$8+$C$13*SQRT($C$8)*O10) -> 202.93608 | R10: =$D$12*EXP(($C$6-$D$15-0.5*$D$13^2)*$C$8+$D$13*SQRT($C$8)*P10) -> 445.8051 | S10: =SUMPRODUCT(Q10:R10,$C$19:$D$19) -> 10379086 | T10: =MAX(S10-$C$7,0) -> 379085.64 | U10: =T10-AE10 -> 659956.47 | W10: Strikes | X10: 175 | Y10: 480 | AA10: =Q10 -> 202.93608 | AB10: =R10 -> 445.8051 | AC10: =MAX(AA10-$X$10,0) -> 27.936077 | AD10: =MAX(AB10-$Y$10,0) -> 0 | AE10: =T10-$AL$7-SUMPRODUCT($AH$17:$AK$17,AA10:AD10) -> -280870.83 | AH10: 176093.47 | AI10: 9995 | AJ10: #N/A | AK10: #N/A | AL10: #N/A
B11: Variables | C11: NVDA | D11: MSFT | G11: ='Call options'!C7 -> 25 | H11: ='Call options'!D7 -> 148.93 | I11: ='Call options'!O7 -> 270 | J11: ='Call options'!P7 -> 239.11 | L11: 6 | M11: =_xlfn.NORM.S.INV(RAND()) -> -2.4874149 | N11: =_xlfn.NORM.S.INV(RAND()) -> 0.581034 | O11: =M11 -> -2.4874149 | P11: =($D$16 * M11) + (SQRT(1 - $D$16^2) * N11) -> -1.1077778 | Q11: =$C$12*EXP(($C$6-$C$15-0.5*$C$13^2)*$C$8+$C$13*SQRT($C$8)*O11) -> 72.303107 | R11: =$D$12*EXP(($C$6-$D$15-0.5*$D$13^2)*$C$8+$D$13*SQRT($C$8)*P11) -> 396.5557 | S11: =SUMPRODUCT(Q11:R11,$C$19:$D$19) -> 6189715.6 | T11: =MAX(S11-$C$7,0) -> 0 | U11: =T11-AE11 -> -16680.29 | W11: Price | X11: =H39 -> 25.5 | Y11: =J29 -> 38.98 | AA11: =Q11 -> 72.303107 | AB11: =R11 -> 396.5557 | AC11: =MAX(AA11-$X$10,0) -> 0 | AD11: =MAX(AB11-$Y$10,0) -> 0 | AE11: =T11-$AL$7-SUMPRODUCT($AH$17:$AK$17,AA11:AD11) -> 16680.29 | AH11: 2.6235511e+16 | AI11: 3.7227946e+14 | AJ11: #N/A | AK11: #N/A | AL11: #N/A
B12: Spot Price | C12: 177 | D12: 476 | G12: ='Call options'!C8 -> 30 | H12: ='Call options'!D8 -> 158.95 | I12: ='Call options'!O8 -> 300 | J12: ='Call options'!P8 -> 186.07 | L12: 7 | M12: =_xlfn.NORM.S.INV(RAND()) -> 0.55146493 | N12: =_xlfn.NORM.S.INV(RAND()) -> -0.90367753 | O12: =M12 -> 0.55146493 | P12: =($D$16 * M12) + (SQRT(1 - $D$16^2) * N12) -> -0.35786512 | Q12: =$C$12*EXP(($C$6-$C$15-0.5*$C$13^2)*$C$8+$C$13*SQRT($C$8)*O12) -> 205.23503 | R12: =$D$12*EXP(($C$6-$D$15-0.5*$D$13^2)*$C$8+$D$13*SQRT($C$8)*P12) -> 448.95958 | S12: =SUMPRODUCT(Q12:R12,$C$19:$D$19) -> 10476793 | T12: =MAX(S12-$C$7,0) -> 476792.85 | U12: =T12-AE12 -> 725294.41 | W12: Share QTY | X12: =AK7 -> -1117.8244 | Y12: =AJ7 -> -231.75765 | AA12: =Q12 -> 205.23503 | AB12: =R12 -> 448.95958 | AC12: =MAX(AA12-$X$10,0) -> 30.23503 | AD12: =MAX(AB12-$Y$10,0) -> 0 | AE12: =T12-$AL$7-SUMPRODUCT($AH$17:$AK$17,AA12:AD12) -> -248501.55
B13: Volatility | C13: =_xlfn.STDEV.S('Historical prices'!H4:H252) * SQRT(252) -> 0.50077432 | D13: =_xlfn.STDEV.S('Historical prices'!P4:P252) * SQRT(252) -> 0.24141784 | G13: ='Call options'!C9 -> 40 | H13: ='Call options'!D9 -> 135.2 | I13: ='Call options'!O9 -> 320 | J13: ='Call options'!P9 -> 203.29 | L13: 8 | M13: =_xlfn.NORM.S.INV(RAND()) -> 0.25818357 | N13: =_xlfn.NORM.S.INV(RAND()) -> -0.42722465 | O13: =M13 -> 0.25818357 | P13: =($D$16 * M13) + (SQRT(1 - $D$16^2) * N13) -> -0.17077103 | Q13: =$C$12*EXP(($C$6-$C$15-0.5*$C$13^2)*$C$8+$C$13*SQRT($C$8)*O13) -> 185.57671 | R13: =$D$12*EXP(($C$6-$D$15-0.5*$D$13^2)*$C$8+$D$13*SQRT($C$8)*P13) -> 463.07933 | S13: =SUMPRODUCT(Q13:R13,$C$19:$D$19) -> 10072043 | T13: =MAX(S13-$C$7,0) -> 72043.491 | U13: =T13-AE13 -> 157066.67 | W13: Option QTY | X13: =AI7 -> 29856.568 | Y13: =AH7 -> 10433.808 | AA13: =Q13 -> 185.57671 | AB13: =R13 -> 463.07933 | AC13: =MAX(AA13-$X$10,0) -> 10.576712 | AD13: =MAX(AB13-$Y$10,0) -> 0 | AE13: =T13-$AL$7-SUMPRODUCT($AH$17:$AK$17,AA13:AD13) -> -85023.183
B14: Annual Dividend | C14: =0.01*4 -> 0.04 | D14: =0.83*4 -> 3.32 | G14: ='Call options'!C10 -> 50 | H14: ='Call options'!D10 -> 122.9 | I14: ='Call options'!O10 -> 330 | J14: ='Call options'!P10 -> 197 | L14: 9 | M14: =_xlfn.NORM.S.INV(RAND()) -> 1.2706745 | N14: =_xlfn.NORM.S.INV(RAND()) -> 0.7519253 | O14: =M14 -> 1.2706745 | P14: =($D$16 * M14) + (SQRT(1 - $D$16^2) * N14) -> 1.3826585 | Q14: =$C$12*EXP(($C$6-$C$15-0.5*$C$13^2)*$C$8+$C$13*SQRT($C$8)*O14) -> 262.71511 | R14: =$D$12*EXP(($C$6-$D$15-0.5*$D$13^2)*$C$8+$D$13*SQRT($C$8)*P14) -> 598.8451 | S14: =SUMPRODUCT(Q14:R14,$C$19:$D$19) -> 13664118 | T14: =MAX(S14-$C$7,0) -> 3664117.9 | U14: =T14-AE14 -> 3582469.7 | AA14: =Q14 -> 262.71511 | AB14: =R14 -> 598.8451 | AC14: =MAX(AA14-$X$10,0) -> 87.715112 | AD14: =MAX(AB14-$Y$10,0) -> 118.8451 | AE14: =T14-$AL$7-SUMPRODUCT($AH$17:$AK$17,AA14:AD14) -> 81648.192
B15: Dividend Yield | C15: =C14/C12 -> 0.0002259887 | D15: =D14/D12 -> 0.0069747899 | G15: ='Call options'!C11 -> 55 | H15: ='Call options'!D11 -> 131.72 | I15: ='Call options'!O11 -> 340 | J15: ='Call options'!P11 -> 200.9 | L15: 10 | M15: =_xlfn.NORM.S.INV(RAND()) -> -0.13120228 | N15: =_xlfn.NORM.S.INV(RAND()) -> -0.46548467 | O15: =M15 -> -0.13120228 | P15: =($D$16 * M15) + (SQRT(1 - $D$16^2) * N15) -> -0.44481897 | Q15: =$C$12*EXP(($C$6-$C$15-0.5*$C$13^2)*$C$8+$C$13*SQRT($C$8)*O15) -> 162.35526 | R15: =$D$12*EXP(($C$6-$D$15-0.5*$D$13^2)*$C$8+$D$13*SQRT($C$8)*P15) -> 442.54463 | S15: =SUMPRODUCT(Q15:R15,$C$19:$D$19) -> 9203858 | T15: =MAX(S15-$C$7,0) -> 0 | U15: =T15-AE15 -> -128001.07 | AA15: =Q15 -> 162.35526 | AB15: =R15 -> 442.54463 | AC15: =MAX(AA15-$X$10,0) -> 0 | AD15: =MAX(AB15-$Y$10,0) -> 0 | AE15: =T15-$AL$7-SUMPRODUCT($AH$17:$AK$17,AA15:AD15) -> 128001.07 | AH15: Share Quantity | AJ15: Options Quantity
B16: Correlation | D16: =CORREL('Historical prices'!H4:H252, 'Historical prices'!P4:P252) -> 0.62727252 | G16: ='Call options'!C12 -> 60 | H16: ='Call options'!D12 -> 124.53 | I16: ='Call options'!O12 -> 350 | J16: ='Call options'!P12 -> 138.8 | L16: 11 | M16: =_xlfn.NORM.S.INV(RAND()) -> 0.37564178 | N16: =_xlfn.NORM.S.INV(RAND()) -> -0.46011518 | O16: =M16 -> 0.37564178 | P16: =($D$16 * M16) + (SQRT(1 - $D$16^2) * N16) -> -0.12270786 | Q16: =$C$12*EXP(($C$6-$C$15-0.5*$C$13^2)*$C$8+$C$13*SQRT($C$8)*O16) -> 193.21302 | R16: =$D$12*EXP(($C$6-$D$15-0.5*$D$13^2)*$C$8+$D$13*SQRT($C$8)*P16) -> 466.77773 | S16: =SUMPRODUCT(Q16:R16,$C$19:$D$19) -> 10325528 | T16: =MAX(S16-$C$7,0) -> 325528.03 | U16: =T16-AE16 -> 375667.59 | AA16: =Q16 -> 193.21302 | AB16: =R16 -> 466.77773 | AC16: =MAX(AA16-$X$10,0) -> 18.213025 | AD16: =MAX(AB16-$Y$10,0) -> 0 | AE16: =T16-$AL$7-SUMPRODUCT($AH$17:$AK$17,AA16:AD16) -> -50139.551 | AH16: NVDA | AI16: MSFT | AJ16: NVDA | AK16: MSFT
B17: Min Strike | C17: ='Call options'!C4 -> 5 | D17: ='Call options'!O4 -> 240 | G17: ='Call options'!C13 -> 65 | H17: ='Call options'!D13 -> 119.75 | I17: ='Call options'!O13 -> 360 | J17: ='Call options'!P13 -> 137.93 | L17: 12 | M17: =_xlfn.NORM.S.INV(RAND()) -> -0.50603477 | N17: =_xlfn.NORM.S.INV(RAND()) -> -1.0903462 | O17: =M17 -> -0.50603477 | P17: =($D$16 * M17) + (SQRT(1 - $D$16^2) * N17) -> -1.1665831 | Q17: =$C$12*EXP(($C$6-$C$15-0.5*$C$13^2)*$C$8+$C$13*SQRT($C$8)*O17) -> 142.75099 | R17: =$D$12*EXP(($C$6-$D$15-0.5*$D$13^2)*$C$8+$D$13*SQRT($C$8)*P17) -> 392.71485 | S17: =SUMPRODUCT(Q17:R17,$C$19:$D$19) -> 8130309.4 | T17: =MAX(S17-$C$7,0) -> 0 | U17: =T17-AE17 -> -94538.507 | AA17: =Q17 -> 142.75099 | AB17: =R17 -> 392.71485 | AC17: =MAX(AA17-$X$10,0) -> 0 | AD17: =MAX(AB17-$Y$10,0) -> 0 | AE17: =T17-$AL$7-SUMPRODUCT($AH$17:$AK$17,AA17:AD17) -> 94538.507 | AH17: =X12 -> -1117.8244 | AI17: =Y12 -> -231.75765 | AJ17: =X13 -> 29856.568 | AK17: =Y13 -> 10433.808
B18: Max Strike | C18: ='Call options'!C62 -> 420 | D18: ='Call options'!O50 -> 800 | G18: ='Call options'!C14 -> 70 | H18: ='Call options'!D14 -> 133.87 | I18: ='Call options'!O14 -> 370 | J18: ='Call options'!P14 -> 146.9 | L18: 13 | M18: =_xlfn.NORM.S.INV(RAND()) -> -0.21565946 | N18: =_xlfn.NORM.S.INV(RAND()) -> -0.33373541 | O18: =M18 -> -0.21565946 | P18: =($D$16 * M18) + (SQRT(1 - $D$16^2) * N18) -> -0.39519034 | Q18: =$C$12*EXP(($C$6-$C$15-0.5*$C$13^2)*$C$8+$C$13*SQRT($C$8)*O18) -> 157.71531 | R18: =$D$12*EXP(($C$6-$D$15-0.5*$D$13^2)*$C$8+$D$13*SQRT($C$8)*P18) -> 446.19463 | S18: =SUMPRODUCT(Q18:R18,$C$19:$D$19) -> 9111651.3 | T18: =MAX(S18-$C$7,0) -> 0 | U18: =T18-AE18 -> -123660.34 | AA18: =Q18 -> 157.71531 | AB18: =R18 -> 446.19463 | AC18: =MAX(AA18-$X$10,0) -> 0 | AD18: =MAX(AB18-$Y$10,0) -> 0 | AE18: =T18-$AL$7-SUMPRODUCT($AH$17:$AK$17,AA18:AD18) -> 123660.34
B19: Number of shares | C19: 28118 | D19: 10482 | G19: ='Call options'!C15 -> 75 | H19: ='Call options'!D15 -> 102.63 | I19: ='Call options'!O15 -> 380 | J19: ='Call options'!P15 -> 111.86 | L19: 14 | M19: =_xlfn.NORM.S.INV(RAND()) -> -1.3459191 | N19: =_xlfn.NORM.S.INV(RAND()) -> 1.7791693 | O19: =M19 -> -1.3459191 | P19: =($D$16 * M19) + (SQRT(1 - $D$16^2) * N19) -> 0.54135872 | Q19: =$C$12*EXP(($C$6-$C$15-0.5*$C$13^2)*$C$8+$C$13*SQRT($C$8)*O19) -> 106.99243 | R19: =$D$12*EXP(($C$6-$D$15-0.5*$D$13^2)*$C$8+$D$13*SQRT($C$8)*P19) -> 521.00589 | S19: =SUMPRODUCT(Q19:R19,$C$19:$D$19) -> 8469597 | T19: =MAX(S19-$C$7,0) -> 0 | U19: =T19-AE19 -> 343548.49 | AA19: =Q19 -> 106.99243 | AB19: =R19 -> 521.00589 | AC19: =MAX(AA19-$X$10,0) -> 0 | AD19: =MAX(AB19-$Y$10,0) -> 41.005893 | AE19: =T19-$AL$7-SUMPRODUCT($AH$17:$AK$17,AA19:AD19) -> -343548.49 | AH19: AVERAGES | AI19: Shares | AK19: Options
G20: ='Call options'!C16 -> 80 | H20: ='Call options'!D16 -> 103.01 | I20: ='Call options'!O16 -> 390 | J20: ='Call options'!P16 -> 94.5 | L20: 15 | M20: =_xlfn.NORM.S.INV(RAND()) -> -0.23793173 | N20: =_xlfn.NORM.S.INV(RAND()) -> 1.3053772 | O20: =M20 -> -0.23793173 | P20: =($D$16 * M20) + (SQRT(1 - $D$16^2) * N20) -> 0.86737954 | Q20: =$C$12*EXP(($C$6-$C$15-0.5*$C$13^2)*$C$8+$C$13*SQRT($C$8)*O20) -> 156.51396 | R20: =$D$12*EXP(($C$6-$D$15-0.5*$D$13^2)*$C$8+$D$13*SQRT($C$8)*P20) -> 549.89113 | S20: =SUMPRODUCT(Q20:R20,$C$19:$D$19) -> 10164818 | T20: =MAX(S20-$C$7,0) -> 164818.43 | U20: =T20-AE20 -> 582880.8 | AA20: =Q20 -> 156.51396 | AB20: =R20 -> 549.89113 | AC20: =MAX(AA20-$X$10,0) -> 0 | AD20: =MAX(AB20-$Y$10,0) -> 69.891133 | AE20: =T20-$AL$7-SUMPRODUCT($AH$17:$AK$17,AA20:AD20) -> -418062.37 | AH20: Basket Payoff | AI20: NVDA | AJ20: MSFT | AK20: NVDA | AL20: MSFT
G21: ='Call options'!C17 -> 85 | H21: ='Call options'!D17 -> 95 | I21: ='Call options'!O17 -> 400 | J21: ='Call options'!P17 -> 95 | L21: 16 | M21: =_xlfn.NORM.S.INV(RAND()) -> 0.66165655 | N21: =_xlfn.NORM.S.INV(RAND()) -> -0.63302428 | O21: =M21 -> 0.66165655 | P21: =($D$16 * M21) + (SQRT(1 - $D$16^2) * N21) -> -0.077960235 | Q21: =$C$12*EXP(($C$6-$C$15-0.5*$C$13^2)*$C$8+$C$13*SQRT($C$8)*O21) -> 213.14786 | R21: =$D$12*EXP(($C$6-$D$15-0.5*$D$13^2)*$C$8+$D$13*SQRT($C$8)*P21) -> 470.24756 | S21: =SUMPRODUCT(Q21:R21,$C$19:$D$19) -> 10922426 | T21: =MAX(S21-$C$7,0) -> 922426.35 | U21: =T21-AE21 -> 947765.47 | AA21: =Q21 -> 213.14786 | AB21: =R21 -> 470.24756 | AC21: =MAX(AA21-$X$10,0) -> 38.147857 | AD21: =MAX(AB21-$Y$10,0) -> 0 | AE21: =T21-$AL$7-SUMPRODUCT($AH$17:$AK$17,AA21:AD21) -> -25339.114 | AH21: =AVERAGE(T6:T10005) -> 985154.1 | AI21: =AVERAGE(AA6:AA10005) -> 179.78075 | AJ21: =AVERAGE(AB6:AB10005) -> 483.17257 | AK21: =AVERAGE(AC6:AC10005) -> 26.665338 | AL21: =AVERAGE(AD6:AD10005) -> 33.1532
G22: ='Call options'!C18 -> 90 | H22: ='Call options'!D18 -> 90.78 | I22: ='Call options'!O18 -> 410 | J22: ='Call options'!P18 -> 80.2 | L22: 17 | M22: =_xlfn.NORM.S.INV(RAND()) -> 0.98204188 | N22: =_xlfn.NORM.S.INV(RAND()) -> 1.428927 | O22: =M22 -> 0.98204188 | P22: =($D$16 * M22) + (SQRT(1 - $D$16^2) * N22) -> 1.728856 | Q22: =$C$12*EXP(($C$6-$C$15-0.5*$C$13^2)*$C$8+$C$13*SQRT($C$8)*O22) -> 237.93053 | R22: =$D$12*EXP(($C$6-$D$15-0.5*$D$13^2)*$C$8+$D$13*SQRT($C$8)*P22) -> 634.16003 | S22: =SUMPRODUCT(Q22:R22,$C$19:$D$19) -> 13337396 | T22: =MAX(S22-$C$7,0) -> 3337395.9 | U22: =T22-AE22 -> 3230476.5 | AA22: =Q22 -> 237.93053 | AB22: =R22 -> 634.16003 | AC22: =MAX(AA22-$X$10,0) -> 62.930526 | AD22: =MAX(AB22-$Y$10,0) -> 154.16003 | AE22: =T22-$AL$7-SUMPRODUCT($AH$17:$AK$17,AA22:AD22) -> 106919.46
G23: ='Call options'!C19 -> 95 | H23: ='Call options'!D19 -> 96.5 | I23: ='Call options'!O19 -> 420 | J23: ='Call options'!P19 -> 78.33 | L23: 18 | M23: =_xlfn.NORM.S.INV(RAND()) -> 1.1071332 | N23: =_xlfn.NORM.S.INV(RAND()) -> 0.079912747 | O23: =M23 -> 1.1071332 | P23: =($D$16 * M23) + (SQRT(1 - $D$16^2) * N23) -> 0.75671025 | Q23: =$C$12*EXP(($C$6-$C$15-0.5*$C$13^2)*$C$8+$C$13*SQRT($C$8)*O23) -> 248.37116 | R23: =$D$12*EXP(($C$6-$D$15-0.5*$D$13^2)*$C$8+$D$13*SQRT($C$8)*P23) -> 539.91067 | S23: =SUMPRODUCT(Q23:R23,$C$19:$D$19) -> 12643044 | T23: =MAX(S23-$C$7,0) -> 2643044 | U23: =T23-AE23 -> 2568990.6 | AA23: =Q23 -> 248.37116 | AB23: =R23 -> 539.91067 | AC23: =MAX(AA23-$X$10,0) -> 73.371165 | AD23: =MAX(AB23-$Y$10,0) -> 59.910667 | AE23: =T23-$AL$7-SUMPRODUCT($AH$17:$AK$17,AA23:AD23) -> 74053.464
G24: ='Call options'!C20 -> 100 | H24: ='Call options'!D20 -> 79.9 | I24: ='Call options'!O20 -> 430 | J24: ='Call options'!P20 -> 67.2 | L24: 19 | M24: =_xlfn.NORM.S.INV(RAND()) -> 0.23064215 | N24: =_xlfn.NORM.S.INV(RAND()) -> 0.2042752 | O24: =M24 -> 0.23064215 | P24: =($D$16 * M24) + (SQRT(1 - $D$16^2) * N24) -> 0.30376498 | Q24: =$C$12*EXP(($C$6-$C$15-0.5*$C$13^2)*$C$8+$C$13*SQRT($C$8)*O24) -> 183.83029 | R24: =$D$12*EXP(($C$6-$D$15-0.5*$D$13^2)*$C$8+$D$13*SQRT($C$8)*P24) -> 500.91566 | S24: =SUMPRODUCT(Q24:R24,$C$19:$D$19) -> 10419538 | T24: =MAX(S24-$C$7,0) -> 419538.07 | U24: =T24-AE24 -> 316337.87 | AA24: =Q24 -> 183.83029 | AB24: =R24 -> 500.91566 | AC24: =MAX(AA24-$X$10,0) -> 8.8302898 | AD24: =MAX(AB24-$Y$10,0) -> 20.915664 | AE24: =T24-$AL$7-SUMPRODUCT($AH$17:$AK$17,AA24:AD24) -> 103200.21 | AH24: VALUATION | AI24: Stocks | AK24: Calls
G25: ='Call options'!C21 -> 105 | H25: ='Call options'!D21 -> 73.8 | I25: ='Call options'!O21 -> 440 | J25: ='Call options'!P21 -> 58.07 | L25: 20 | M25: =_xlfn.NORM.S.INV(RAND()) -> 0.59946231 | N25: =_xlfn.NORM.S.INV(RAND()) -> 0.23725768 | O25: =M25 -> 0.59946231 | P25: =($D$16 * M25) + (SQRT(1 - $D$16^2) * N25) -> 0.56080248 | Q25: =$C$12*EXP(($C$6-$C$15-0.5*$C$13^2)*$C$8+$C$13*SQRT($C$8)*O25) -> 208.64494 | R25: =$D$12*EXP(($C$6-$D$15-0.5*$D$13^2)*$C$8+$D$13*SQRT($C$8)*P25) -> 522.68524 | S25: =SUMPRODUCT(Q25:R25,$C$19:$D$19) -> 11345465 | T25: =MAX(S25-$C$7,0) -> 1345465.1 | U25: =T25-AE25 -> 1251574.1 | AA25: =Q25 -> 208.64494 | AB25: =R25 -> 522.68524 | AC25: =MAX(AA25-$X$10,0) -> 33.644942 | AD25: =MAX(AB25-$Y$10,0) -> 42.685239 | AE25: =T25-$AL$7-SUMPRODUCT($AH$17:$AK$17,AA25:AD25) -> 93891.036 | AH25: Const | AI25: NVDA | AJ25: MSFT | AK25: NVDA | AL25: MSFT
G26: ='Call options'!C22 -> 110 | H26: ='Call options'!D22 -> 69.11 | I26: ='Call options'!O22 -> 450 | J26: ='Call options'!P22 -> 57.19 | L26: 21 | M26: =_xlfn.NORM.S.INV(RAND()) -> 0.87868107 | N26: =_xlfn.NORM.S.INV(RAND()) -> -0.51985714 | O26: =M26 -> 0.87868107 | P26: =($D$16 * M26) + (SQRT(1 - $D$16^2) * N26) -> 0.14630784 | Q26: =$C$12*EXP(($C$6-$C$15-0.5*$C$13^2)*$C$8+$C$13*SQRT($C$8)*O26) -> 229.63557 | R26: =$D$12*EXP(($C$6-$D$15-0.5*$D$13^2)*$C$8+$D$13*SQRT($C$8)*P26) -> 488.03024 | S26: =SUMPRODUCT(Q26:R26,$C$19:$D$19) -> 11572426 | T26: =MAX(S26-$C$7,0) -> 1572425.8 | U26: =T26-AE26 -> 1501266.2 | AA26: =Q26 -> 229.63557 | AB26: =R26 -> 488.03024 | AC26: =MAX(AA26-$X$10,0) -> 54.635565 | AD26: =MAX(AB26-$Y$10,0) -> 8.0302426 | AE26: =T26-$AL$7-SUMPRODUCT($AH$17:$AK$17,AA26:AD26) -> 71159.592 | AH26: =AL7*C9 -> 153306.06 | AI26: =X9*X12 -> -197854.91 | AJ26: =Y9*Y12 -> -110316.64 | AK26: =X11*X13 -> 761342.5 | AL26: =Y11*Y13 -> 406709.85
G27: ='Call options'!C23 -> 115 | H27: ='Call options'!D23 -> 64.8 | I27: ='Call options'!O23 -> 460 | J27: ='Call options'!P23 -> 50.38 | L27: 22 | M27: =_xlfn.NORM.S.INV(RAND()) -> 2.6353518 | N27: =_xlfn.NORM.S.INV(RAND()) -> 0.8503363 | O27: =M27 -> 2.6353518 | P27: =($D$16 * M27) + (SQRT(1 - $D$16^2) * N27) -> 2.3153255 | Q27: =$C$12*EXP(($C$6-$C$15-0.5*$C$13^2)*$C$8+$C$13*SQRT($C$8)*O27) -> 419.71775 | R27: =$D$12*EXP(($C$6-$D$15-0.5*$D$13^2)*$C$8+$D$13*SQRT($C$8)*P27) -> 698.8014 | S27: =SUMPRODUCT(Q27:R27,$C$19:$D$19) -> 19126460 | T27: =MAX(S27-$C$7,0) -> 9126460.1 | U27: =T27-AE27 -> 9114287.6 | AA27: =Q27 -> 419.71775 | AB27: =R27 -> 698.8014 | AC27: =MAX(AA27-$X$10,0) -> 244.71775 | AD27: =MAX(AB27-$Y$10,0) -> 218.8014 | AE27: =T27-$AL$7-SUMPRODUCT($AH$17:$AK$17,AA27:AD27) -> 12172.42
G28: ='Call options'!C24 -> 120 | H28: ='Call options'!D24 -> 60.7 | I28: ='Call options'!O24 -> 470 | J28: ='Call options'!P24 -> 45.1 | L28: 23 | M28: =_xlfn.NORM.S.INV(RAND()) -> 0.6780987 | N28: =_xlfn.NORM.S.INV(RAND()) -> -0.2969125 | O28: =M28 -> 0.6780987 | P28: =($D$16 * M28) + (SQRT(1 - $D$16^2) * N28) -> 0.19411728 | Q28: =$C$12*EXP(($C$6-$C$15-0.5*$C$13^2)*$C$8+$C$13*SQRT($C$8)*O28) -> 214.35444 | R28: =$D$12*EXP(($C$6-$D$15-0.5*$D$13^2)*$C$8+$D$13*SQRT($C$8)*P28) -> 491.90726 | S28: =SUMPRODUCT(Q28:R28,$C$19:$D$19) -> 11183390 | T28: =MAX(S28-$C$7,0) -> 1183390 | U28: =T28-AE28 -> 1101659.4 | AA28: =Q28 -> 214.35444 | AB28: =R28 -> 491.90726 | AC28: =MAX(AA28-$X$10,0) -> 39.354439 | AD28: =MAX(AB28-$Y$10,0) -> 11.907263 | AE28: =T28-$AL$7-SUMPRODUCT($AH$17:$AK$17,AA28:AD28) -> 81730.629 | AH28: SUM | AI28: =SUM(AH26:AL26) -> 1013186.9
G29: ='Call options'!C25 -> 125 | H29: ='Call options'!D25 -> 59.25 | I29: ='Call options'!O25 -> 480 | J29: ='Call options'!P25 -> 38.98 | L29: 24 | M29: =_xlfn.NORM.S.INV(RAND()) -> 0.22667049 | N29: =_xlfn.NORM.S.INV(RAND()) -> 0.039589611 | O29: =M29 -> 0.22667049 | P29: =($D$16 * M29) + (SQRT(1 - $D$16^2) * N29) -> 0.17301655 | Q29: =$C$12*EXP(($C$6-$C$15-0.5*$C$13^2)*$C$8+$C$13*SQRT($C$8)*O29) -> 183.5798 | R29: =$D$12*EXP(($C$6-$D$15-0.5*$D$13^2)*$C$8+$D$13*SQRT($C$8)*P29) -> 490.19236 | S29: =SUMPRODUCT(Q29:R29,$C$19:$D$19) -> 10300093 | T29: =MAX(S29-$C$7,0) -> 300093.18 | U29: =T29-AE29 -> 199739.47 | AA29: =Q29 -> 183.5798 | AB29: =R29 -> 490.19236 | AC29: =MAX(AA29-$X$10,0) -> 8.5798035 | AD29: =MAX(AB29-$Y$10,0) -> 10.192355 | AE29: =T29-$AL$7-SUMPRODUCT($AH$17:$AK$17,AA29:AD29) -> 100353.71
G30: ='Call options'!C26 -> 130 | H30: ='Call options'!D26 -> 54.2 | I30: ='Call options'!O26 -> 490 | J30: ='Call options'!P26 -> 34.08 | L30: 25 | M30: =_xlfn.NORM.S.INV(RAND()) -> -0.98959422 | N30: =_xlfn.NORM.S.INV(RAND()) -> -1.5971858 | O30: =M30 -> -0.98959422 | P30: =($D$16 * M30) + (SQRT(1 - $D$16^2) * N30) -> -1.8646333 | Q30: =$C$12*EXP(($C$6-$C$15-0.5*$C$13^2)*$C$8+$C$13*SQRT($C$8)*O30) -> 120.91518 | R30: =$D$12*EXP(($C$6-$D$15-0.5*$D$13^2)*$C$8+$D$13*SQRT($C$8)*P30) -> 349.8663 | S30: =SUMPRODUCT(Q30:R30,$C$19:$D$19) -> 7067191.4 | T30: =MAX(S30-$C$7,0) -> 0 | U30: =T30-AE30 -> -60199.42 | AA30: =Q30 -> 120.91518 | AB30: =R30 -> 349.8663 | AC30: =MAX(AA30-$X$10,0) -> 0 | AD30: =MAX(AB30-$Y$10,0) -> 0 | AE30: =T30-$AL$7-SUMPRODUCT($AH$17:$AK$17,AA30:AD30) -> 60199.42 | AH30: Residual
G31: ='Call options'!C27 -> 135 | H31: ='Call options'!D27 -> 49.98 | I31: ='Call options'!O27 -> 500 | J31: ='Call options'!P27 -> 29.35 | L31: 26 | M31: =_xlfn.NORM.S.INV(RAND()) -> 1.2058477 | N31: =_xlfn.NORM.S.INV(RAND()) -> 0.51953057 | O31: =M31 -> 1.2058477 | P31: =($D$16 * M31) + (SQRT(1 - $D$16^2) * N31) -> 1.1610055 | Q31: =$C$12*EXP(($C$6-$C$15-0.5*$C$13^2)*$C$8+$C$13*SQRT($C$8)*O31) -> 256.93273 | R31: =$D$12*EXP(($C$6-$D$15-0.5*$D$13^2)*$C$8+$D$13*SQRT($C$8)*P31) -> 577.27438 | S31: =SUMPRODUCT(Q31:R31,$C$19:$D$19) -> 13275425 | T31: =MAX(S31-$C$7,0) -> 3275424.6 | U31: =T31-AE31 -> 3196225.8 | AA31: =Q31 -> 256.93273 | AB31: =R31 -> 577.27438 | AC31: =MAX(AA31-$X$10,0) -> 81.932733 | AD31: =MAX(AB31-$Y$10,0) -> 97.274379 | AE31: =T31-$AL$7-SUMPRODUCT($AH$17:$AK$17,AA31:AD31) -> 79198.863 | AH31: Average | AI31: =AVERAGE(AE6:AE10005) -> -5.3550466e-10
G32: ='Call options'!C28 -> 140 | H32: ='Call options'!D28 -> 47.45 | I32: ='Call options'!O28 -> 510 | J32: ='Call options'!P28 -> 25.5 | L32: 27 | M32: =_xlfn.NORM.S.INV(RAND()) -> 1.0888588 | N32: =_xlfn.NORM.S.INV(RAND()) -> 0.77895635 | O32: =M32 -> 1.0888588 | P32: =($D$16 * M32) + (SQRT(1 - $D$16^2) * N32) -> 1.2896623 | Q32: =$C$12*EXP(($C$6-$C$15-0.5*$C$13^2)*$C$8+$C$13*SQRT($C$8)*O32) -> 246.8178 | R32: =$D$12*EXP(($C$6-$D$15-0.5*$D$13^2)*$C$8+$D$13*SQRT($C$8)*P32) -> 589.69849 | S32: =SUMPRODUCT(Q32:R32,$C$19:$D$19) -> 13121243 | T32: =MAX(S32-$C$7,0) -> 3121242.5 | U32: =T32-AE32 -> 3032286.7 | AA32: =Q32 -> 246.8178 | AB32: =R32 -> 589.69849 | AC32: =MAX(AA32-$X$10,0) -> 71.817801 | AD32: =MAX(AB32-$Y$10,0) -> 109.69849 | AE32: =T32-$AL$7-SUMPRODUCT($AH$17:$AK$17,AA32:AD32) -> 88955.768 | AH32: 5 Percentile | AI32: =PERCENTILE(AE6:AE10005,0.05) -> -436768.55
G33: ='Call options'!C29 -> 145 | H33: ='Call options'!D29 -> 43.03 | I33: ='Call options'!O29 -> 520 | J33: ='Call options'!P29 -> 21.58 | L33: 28 | M33: =_xlfn.NORM.S.INV(RAND()) -> -1.1853018 | N33: =_xlfn.NORM.S.INV(RAND()) -> 0.75309982 | O33: =M33 -> -1.1853018 | P33: =($D$16 * M33) + (SQRT(1 - $D$16^2) * N33) -> -0.15699326 | Q33: =$C$12*EXP(($C$6-$C$15-0.5*$C$13^2)*$C$8+$C$13*SQRT($C$8)*O33) -> 113.05791 | R33: =$D$12*EXP(($C$6-$D$15-0.5*$D$13^2)*$C$8+$D$13*SQRT($C$8)*P33) -> 464.1365 | S33: =SUMPRODUCT(Q33:R33,$C$19:$D$19) -> 8044041.3 | T33: =MAX(S33-$C$7,0) -> 0 | U33: =T33-AE33 -> -77899.375 | AA33: =Q33 -> 113.05791 | AB33: =R33 -> 464.1365 | AC33: =MAX(AA33-$X$10,0) -> 0 | AD33: =MAX(AB33-$Y$10,0) -> 0 | AE33: =T33-$AL$7-SUMPRODUCT($AH$17:$AK$17,AA33:AD33) -> 77899.375 | AH33: Raroc | AI33: 0.25
G34: ='Call options'!C30 -> 150 | H34: ='Call options'!D30 -> 38.7 | I34: ='Call options'!O30 -> 530 | J34: ='Call options'!P30 -> 18.55 | L34: 29 | M34: =_xlfn.NORM.S.INV(RAND()) -> 0.19785417 | N34: =_xlfn.NORM.S.INV(RAND()) -> -0.49639791 | O34: =M34 -> 0.19785417 | P34: =($D$16 * M34) + (SQRT(1 - $D$16^2) * N34) -> -0.26248613 | Q34: =$C$12*EXP(($C$6-$C$15-0.5*$C$13^2)*$C$8+$C$13*SQRT($C$8)*O34) -> 181.7726 | R34: =$D$12*EXP(($C$6-$D$15-0.5*$D$13^2)*$C$8+$D$13*SQRT($C$8)*P34) -> 456.10307 | S34: =SUMPRODUCT(Q34:R34,$C$19:$D$19) -> 9891954.2 | T34: =MAX(S34-$C$7,0) -> 0 | U34: =T34-AE34 -> 49357.964 | AA34: =Q34 -> 181.7726 | AB34: =R34 -> 456.10307 | AC34: =MAX(AA34-$X$10,0) -> 6.772596 | AD34: =MAX(AB34-$Y$10,0) -> 0 | AE34: =T34-$AL$7-SUMPRODUCT($AH$17:$AK$17,AA34:AD34) -> -49357.964 | AH34: Risk Charge | AI34: =AI32*AI33 -> -109192.14
G35: ='Call options'!C31 -> 155 | H35: ='Call options'!D31 -> 36.96 | I35: ='Call options'!O31 -> 540 | J35: ='Call options'!P31 -> 15.85 | L35: 30 | M35: =_xlfn.NORM.S.INV(RAND()) -> 1.7341472 | N35: =_xlfn.NORM.S.INV(RAND()) -> -0.058996026 | O35: =M35 -> 1.7341472 | P35: =($D$16 * M35) + (SQRT(1 - $D$16^2) * N35) -> 1.0418368 | Q35: =$C$12*EXP(($C$6-$C$15-0.5*$C$13^2)*$C$8+$C$13*SQRT($C$8)*O35) -> 308.02677 | R35: =$D$12*EXP(($C$6-$D$15-0.5*$D$13^2)*$C$8+$D$13*SQRT($C$8)*P35) -> 566.00015 | S35: =SUMPRODUCT(Q35:R35,$C$19:$D$19) -> 14593910 | T35: =MAX(S35-$C$7,0) -> 4593910.2 | U35: =T35-AE35 -> 4549583.8 | AA35: =Q35 -> 308.02677 | AB35: =R35 -> 566.00015 | AC35: =MAX(AA35-$X$10,0) -> 133.02677 | AD35: =MAX(AB35-$Y$10,0) -> 86.000148 | AE35: =T35-$AL$7-SUMPRODUCT($AH$17:$AK$17,AA35:AD35) -> 44326.333
G36: ='Call options'!C32 -> 160 | H36: ='Call options'!D32 -> 33 | I36: ='Call options'!O32 -> 550 | J36: ='Call options'!P32 -> 13.15 | L36: 31 | M36: =_xlfn.NORM.S.INV(RAND()) -> 1.279745 | N36: =_xlfn.NORM.S.INV(RAND()) -> -0.59930798 | O36: =M36 -> 1.279745 | P36: =($D$16 * M36) + (SQRT(1 - $D$16^2) * N36) -> 0.33600793 | Q36: =$C$12*EXP(($C$6-$C$15-0.5*$C$13^2)*$C$8+$C$13*SQRT($C$8)*O36) -> 263.53449 | R36: =$D$12*EXP(($C$6-$D$15-0.5*$D$13^2)*$C$8+$D$13*SQRT($C$8)*P36) -> 503.59592 | S36: =SUMPRODUCT(Q36:R36,$C$19:$D$19) -> 12688755 | T36: =MAX(S36-$C$7,0) -> 2688755.3 | U36: =T36-AE36 -> 2634280.7 | AA36: =Q36 -> 263.53449 | AB36: =R36 -> 503.59592 | AC36: =MAX(AA36-$X$10,0) -> 88.534491 | AD36: =MAX(AB36-$Y$10,0) -> 23.595924 | AE36: =T36-$AL$7-SUMPRODUCT($AH$17:$AK$17,AA36:AD36) -> 54474.635
G37: ='Call options'!C33 -> 165 | H37: ='Call options'!D33 -> 30.67 | I37: ='Call options'!O33 -> 560 | J37: ='Call options'!P33 -> 10.95 | L37: 32 | M37: =_xlfn.NORM.S.INV(RAND()) -> 0.85211418 | N37: =_xlfn.NORM.S.INV(RAND()) -> 1.2832513 | O37: =M37 -> 0.85211418 | P37: =($D$16 * M37) + (SQRT(1 - $D$16^2) * N37) -> 1.5339037 | Q37: =$C$12*EXP(($C$6-$C$15-0.5*$C$13^2)*$C$8+$C$13*SQRT($C$8)*O37) -> 227.55063 | R37: =$D$12*EXP(($C$6-$D$15-0.5*$D$13^2)*$C$8+$D$13*SQRT($C$8)*P37) -> 614.02474 | S37: =SUMPRODUCT(Q37:R37,$C$19:$D$19) -> 12834476 | T37: =MAX(S37-$C$7,0) -> 2834476.1 | U37: =T37-AE37 -> 2726750.2 | AA37: =Q37 -> 227.55063 | AB37: =R37 -> 614.02474 | AC37: =MAX(AA37-$X$10,0) -> 52.550634 | AD37: =MAX(AB37-$Y$10,0) -> 134.02474 | AE37: =T37-$AL$7-SUMPRODUCT($AH$17:$AK$17,AA37:AD37) -> 107725.86 | AH37: VALUATION TO MD | AI37: =AI28-AI34 -> 1122379
G38: ='Call options'!C34 -> 170 | H38: ='Call options'!D34 -> 28 | I38: ='Call options'!O34 -> 570 | J38: ='Call options'!P34 -> 9.3 | L38: 33 | M38: =_xlfn.NORM.S.INV(RAND()) -> -0.67888223 | N38: =_xlfn.NORM.S.INV(RAND()) -> 0.9938393 | O38: =M38 -> -0.67888223 | P38: =($D$16 * M38) + (SQRT(1 - $D$16^2) * N38) -> 0.34815771 | Q38: =$C$12*EXP(($C$6-$C$15-0.5*$C$13^2)*$C$8+$C$13*SQRT($C$8)*O38) -> 134.52646 | R38: =$D$12*EXP(($C$6-$D$15-0.5*$D$13^2)*$C$8+$D$13*SQRT($C$8)*P38) -> 504.60962 | S38: =SUMPRODUCT(Q38:R38,$C$19:$D$19) -> 9071933.1 | T38: =MAX(S38-$C$7,0) -> 0 | U38: =T38-AE38 -> 145494.62 | AA38: =Q38 -> 134.52646 | AB38: =R38 -> 504.60962 | AC38: =MAX(AA38-$X$10,0) -> 0 | AD38: =MAX(AB38-$Y$10,0) -> 24.609616 | AE38: =T38-$AL$7-SUMPRODUCT($AH$17:$AK$17,AA38:AD38) -> -145494.62
G39: ='Call options'!C35 -> 175 | H39: ='Call options'!D35 -> 25.5 | I39: ='Call options'!O35 -> 580 | J39: ='Call options'!P35 -> 7.05 | L39: 34 | M39: =_xlfn.NORM.S.INV(RAND()) -> -1.5389262 | N39: =_xlfn.NORM.S.INV(RAND()) -> -0.22316801 | O39: =M39 -> -1.5389262 | P39: =($D$16 * M39) + (SQRT(1 - $D$16^2) * N39) -> -1.1391293 | Q39: =$C$12*EXP(($C$6-$C$15-0.5*$C$13^2)*$C$8+$C$13*SQRT($C$8)*O39) -> 100.13269 | R39: =$D$12*EXP(($C$6-$D$15-0.5*$D$13^2)*$C$8+$D$13*SQRT($C$8)*P39) -> 394.50333 | S39: =SUMPRODUCT(Q39:R39,$C$19:$D$19) -> 6950714.8 | T39: =MAX(S39-$C$7,0) -> 0 | U39: =T39-AE39 -> -47313.22 | AA39: =Q39 -> 100.13269 | AB39: =R39 -> 394.50333 | AC39: =MAX(AA39-$X$10,0) -> 0 | AD39: =MAX(AB39-$Y$10,0) -> 0 | AE39: =T39-$AL$7-SUMPRODUCT($AH$17:$AK$17,AA39:AD39) -> 47313.22
G40: ='Call options'!C36 -> 180 | H40: ='Call options'!D36 -> 22.9 | I40: ='Call options'!O36 -> 590 | J40: ='Call options'!P36 -> 6.4 | L40: 35 | M40: =_xlfn.NORM.S.INV(RAND()) -> 0.63359721 | N40: =_xlfn.NORM.S.INV(RAND()) -> 2.333438 | O40: =M40 -> 0.63359721 | P40: =($D$16 * M40) + (SQRT(1 - $D$16^2) * N40) -> 2.2147193 | Q40: =$C$12*EXP(($C$6-$C$15-0.5*$C$13^2)*$C$8+$C$13*SQRT($C$8)*O40) -> 211.10443 | R40: =$D$12*EXP(($C$6-$D$15-0.5*$D$13^2)*$C$8+$D$13*SQRT($C$8)*P40) -> 687.26191 | S40: =SUMPRODUCT(Q40:R40,$C$19:$D$19) -> 13139714 | T40: =MAX(S40-$C$7,0) -> 3139713.7 | U40: =T40-AE40 -> 3001276.3 | AA40: =Q40 -> 211.10443 | AB40: =R40 -> 687.26191 | AC40: =MAX(AA40-$X$10,0) -> 36.104429 | AD40: =MAX(AB40-$Y$10,0) -> 207.26191 | AE40: =T40-$AL$7-SUMPRODUCT($AH$17:$AK$17,AA40:AD40) -> 138437.43
G41: ='Call options'!C37 -> 185 | H41: ='Call options'!D37 -> 20.65 | I41: ='Call options'!O37 -> 600 | J41: ='Call options'!P37 -> 5.39 | L41: 36 | M41: =_xlfn.NORM.S.INV(RAND()) -> 0.52668994 | N41: =_xlfn.NORM.S.INV(RAND()) -> -0.36910137 | O41: =M41 -> 0.52668994 | P41: =($D$16 * M41) + (SQRT(1 - $D$16^2) * N41) -> 0.042922037 | Q41: =$C$12*EXP(($C$6-$C$15-0.5*$C$13^2)*$C$8+$C$13*SQRT($C$8)*O41) -> 203.49679 | R41: =$D$12*EXP(($C$6-$D$15-0.5*$D$13^2)*$C$8+$D$13*SQRT($C$8)*P41) -> 479.75052 | S41: =SUMPRODUCT(Q41:R41,$C$19:$D$19) -> 10750668 | T41: =MAX(S41-$C$7,0) -> 750667.66 | U41: =T41-AE41 -> 668203.46 | AA41: =Q41 -> 203.49679 | AB41: =R41 -> 479.75052 | AC41: =MAX(AA41-$X$10,0) -> 28.496787 | AD41: =MAX(AB41-$Y$10,0) -> 0 | AE41: =T41-$AL$7-SUMPRODUCT($AH$17:$AK$17,AA41:AD41) -> 82464.199
G42: ='Call options'!C38 -> 190 | H42: ='Call options'!D38 -> 18.6 | I42: ='Call options'!O38 -> 610 | J42: ='Call options'!P38 -> 3.87 | L42: 37 | M42: =_xlfn.NORM.S.INV(RAND()) -> -1.1414992 | N42: =_xlfn.NORM.S.INV(RAND()) -> -0.80604698 | O42: =M42 -> -1.1414992 | P42: =($D$16 * M42) + (SQRT(1 - $D$16^2) * N42) -> -1.3437803 | Q42: =$C$12*EXP(($C$6-$C$15-0.5*$C$13^2)*$C$8+$C$13*SQRT($C$8)*O42) -> 114.77093 | R42: =$D$12*EXP(($C$6-$D$15-0.5*$D$13^2)*$C$8+$D$13*SQRT($C$8)*P42) -> 381.36475 | S42: =SUMPRODUCT(Q42:R42,$C$19:$D$19) -> 7224594.3 | T42: =MAX(S42-$C$7,0) -> 0 | U42: =T42-AE42 -> -60631.24 | AA42: =Q42 -> 114.77093 | AB42: =R42 -> 381.36475 | AC42: =MAX(AA42-$X$10,0) -> 0 | AD42: =MAX(AB42-$Y$10,0) -> 0 | AE42: =T42-$AL$7-SUMPRODUCT($AH$17:$AK$17,AA42:AD42) -> 60631.24
G43: ='Call options'!C39 -> 195 | H43: ='Call options'!D39 -> 16.64 | I43: ='Call options'!O39 -> 620 | J43: ='Call options'!P39 -> 3.62 | L43: 38 | M43: =_xlfn.NORM.S.INV(RAND()) -> -0.60410244 | N43: =_xlfn.NORM.S.INV(RAND()) -> -1.1386524 | O43: =M43 -> -0.60410244 | P43: =($D$16 * M43) + (SQRT(1 - $D$16^2) * N43) -> -1.2657192 | Q43: =$C$12*EXP(($C$6-$C$15-0.5*$C$13^2)*$C$8+$C$13*SQRT($C$8)*O43) -> 138.02486 | R43: =$D$12*EXP(($C$6-$D$15-0.5*$D$13^2)*$C$8+$D$13*SQRT($C$8)*P43) -> 386.32384 | S43: =SUMPRODUCT(Q43:R43,$C$19:$D$19) -> 7930429.6 | T43: =MAX(S43-$C$7,0) -> 0 | U43: =T43-AE43 -> -87774.361 | AA43: =Q43 -> 138.02486 | AB43: =R43 -> 386.32384 | AC43: =MAX(AA43-$X$10,0) -> 0 | AD43: =MAX(AB43-$Y$10,0) -> 0 | AE43: =T43-$AL$7-SUMPRODUCT($AH$17:$AK$17,AA43:AD43) -> 87774.361
G44: ='Call options'!C40 -> 200 | H44: ='Call options'!D40 -> 14.91 | I44: ='Call options'!O40 -> 630 | J44: ='Call options'!P40 -> 3.1 | L44: 39 | M44: =_xlfn.NORM.S.INV(RAND()) -> 0.66474535 | N44: =_xlfn.NORM.S.INV(RAND()) -> 0.17920495 | O44: =M44 -> 0.66474535 | P44: =($D$16 * M44) + (SQRT(1 - $D$16^2) * N44) -> 0.55654128 | Q44: =$C$12*EXP(($C$6-$C$15-0.5*$C$13^2)*$C$8+$C$13*SQRT($C$8)*O44) -> 213.374 | R44: =$D$12*EXP(($C$6-$D$15-0.5*$D$13^2)*$C$8+$D$13*SQRT($C$8)*P44) -> 522.31674 | S44: =SUMPRODUCT(Q44:R44,$C$19:$D$19) -> 11474574 | T44: =MAX(S44-$C$7,0) -> 1474574.3 | U44: =T44-AE44 -> 1383722 | AA44: =Q44 -> 213.374 | AB44: =R44 -> 522.31674 | AC44: =MAX(AA44-$X$10,0) -> 38.374004 | AD44: =MAX(AB44-$Y$10,0) -> 42.316739 | AE44: =T44-$AL$7-SUMPRODUCT($AH$17:$AK$17,AA44:AD44) -> 90852.337
G45: ='Call options'!C41 -> 210 | H45: ='Call options'!D41 -> 11.8 | I45: ='Call options'!O41 -> 640 | J45: ='Call options'!P41 -> 2.55 | L45: 40 | M45: =_xlfn.NORM.S.INV(RAND()) -> 0.3660989 | N45: =_xlfn.NORM.S.INV(RAND()) -> -0.0098882822 | O45: =M45 -> 0.3660989 | P45: =($D$16 * M45) + (SQRT(1 - $D$16^2) * N45) -> 0.22194279 | Q45: =$C$12*EXP(($C$6-$C$15-0.5*$C$13^2)*$C$8+$C$13*SQRT($C$8)*O45) -> 192.58106 | R45: =$D$12*EXP(($C$6-$D$15-0.5*$D$13^2)*$C$8+$D$13*SQRT($C$8)*P45) -> 494.17789 | S45: =SUMPRODUCT(Q45:R45,$C$19:$D$19) -> 10594967 | T45: =MAX(S45-$C$7,0) -> 594966.74 | U45: =T45-AE45 -> 499084.75 | AA45: =Q45 -> 192.58106 | AB45: =R45 -> 494.17789 | AC45: =MAX(AA45-$X$10,0) -> 17.581056 | AD45: =MAX(AB45-$Y$10,0) -> 14.177886 | AE45: =T45-$AL$7-SUMPRODUCT($AH$17:$AK$17,AA45:AD45) -> 95881.987
G46: ='Call options'!C42 -> 220 | H46: ='Call options'!D42 -> 9.29 | I46: ='Call options'!O42 -> 650 | J46: ='Call options'!P42 -> 2.11 | L46: 41 | M46: =_xlfn.NORM.S.INV(RAND()) -> 0.73404992 | N46: =_xlfn.NORM.S.INV(RAND()) -> -2.5775451 | O46: =M46 -> 0.73404992 | P46: =($D$16 * M46) + (SQRT(1 - $D$16^2) * N46) -> -1.5469424 | Q46: =$C$12*EXP(($C$6-$C$15-0.5*$C$13^2)*$C$8+$C$13*SQRT($C$8)*O46) -> 218.51173 | R46: =$D$12*EXP(($C$6-$D$15-0.5*$D$13^2)*$C$8+$D$13*SQRT($C$8)*P46) -> 368.7546 | S46: =SUMPRODUCT(Q46:R46,$C$19:$D$19) -> 10009399 | T46: =MAX(S46-$C$7,0) -> 9398.6302 | U46: =T46-AE46 -> 1125438.3 | AA46: =Q46 -> 218.51173 | AB46: =R46 -> 368.7546 | AC46: =MAX(AA46-$X$10,0) -> 43.511734 | AD46: =MAX(AB46-$Y$10,0) -> 0 | AE46: =T46-$AL$7-SUMPRODUCT($AH$17:$AK$17,AA46:AD46) -> -1116039.7
G47: ='Call options'!C43 -> 230 | H47: ='Call options'!D43 -> 7.44 | I47: ='Call options'!O43 -> 660 | J47: ='Call options'!P43 -> 1.73 | L47: 42 | M47: =_xlfn.NORM.S.INV(RAND()) -> -1.0073264 | N47: =_xlfn.NORM.S.INV(RAND()) -> -0.35111036 | O47: =M47 -> -1.0073264 | P47: =($D$16 * M47) + (SQRT(1 - $D$16^2) * N47) -> -0.90531284 | Q47: =$C$12*EXP(($C$6-$C$15-0.5*$C$13^2)*$C$8+$C$13*SQRT($C$8)*O47) -> 120.18132 | R47: =$D$12*EXP(($C$6-$D$15-0.5*$D$13^2)*$C$8+$D$13*SQRT($C$8)*P47) -> 410.06924 | S47: =SUMPRODUCT(Q47:R47,$C$19:$D$19) -> 7677604.1 | T47: =MAX(S47-$C$7,0) -> 0 | U47: =T47-AE47 -> -73331.589 | AA47: =Q47 -> 120.18132 | AB47: =R47 -> 410.06924 | AC47: =MAX(AA47-$X$10,0) -> 0 | AD47: =MAX(AB47-$Y$10,0) -> 0 | AE47: =T47-$AL$7-SUMPRODUCT($AH$17:$AK$17,AA47:AD47) -> 73331.589
G48: ='Call options'!C44 -> 240 | H48: ='Call options'!D44 -> 5.15 | I48: ='Call options'!O44 -> 680 | J48: ='Call options'!P44 -> 0.92 | L48: 43 | M48: =_xlfn.NORM.S.INV(RAND()) -> -0.2979896 | N48: =_xlfn.NORM.S.INV(RAND()) -> 0.41174474 | O48: =M48 -> -0.2979896 | P48: =($D$16 * M48) + (SQRT(1 - $D$16^2) * N48) -> 0.13374605 | Q48: =$C$12*EXP(($C$6-$C$15-0.5*$C$13^2)*$C$8+$C$13*SQRT($C$8)*O48) -> 153.31989 | R48: =$D$12*EXP(($C$6-$D$15-0.5*$D$13^2)*$C$8+$D$13*SQRT($C$8)*P48) -> 487.01665 | S48: =SUMPRODUCT(Q48:R48,$C$19:$D$19) -> 9415957.2 | T48: =MAX(S48-$C$7,0) -> 0 | U48: =T48-AE48 -> -54997.499 | AA48: =Q48 -> 153.31989 | AB48: =R48 -> 487.01665 | AC48: =MAX(AA48-$X$10,0) -> 0 | AD48: =MAX(AB48-$Y$10,0) -> 7.0166464 | AE48: =T48-$AL$7-SUMPRODUCT($AH$17:$AK$17,AA48:AD48) -> 54997.499
G49: ='Call options'!C45 -> 250 | H49: ='Call options'!D45 -> 4.64 | I49: ='Call options'!O45 -> 700 | J49: ='Call options'!P45 -> 0.82 | L49: 44 | M49: =_xlfn.NORM.S.INV(RAND()) -> -0.59477937 | N49: =_xlfn.NORM.S.INV(RAND()) -> 0.64701892 | O49: =M49 -> -0.59477937 | P49: =($D$16 * M49) + (SQRT(1 - $D$16^2) * N49) -> 0.13080947 | Q49: =$C$12*EXP(($C$6-$C$15-0.5*$C$13^2)*$C$8+$C$13*SQRT($C$8)*O49) -> 138.46735 | R49: =$D$12*EXP(($C$6-$D$15-0.5*$D$13^2)*$C$8+$D$13*SQRT($C$8)*P49) -> 486.78 | S49: =SUMPRODUCT(Q49:R49,$C$19:$D$19) -> 8995853 | T49: =MAX(S49-$C$7,0) -> 0 | U49: =T49-AE49 -> -40809.241 | AA49: =Q49 -> 138.46735 | AB49: =R49 -> 486.78 | AC49: =MAX(AA49-$X$10,0) -> 0 | AD49: =MAX(AB49-$Y$10,0) -> 6.7800006 | AE49: =T49-$AL$7-SUMPRODUCT($AH$17:$AK$17,AA49:AD49) -> 40809.241
... G54: ='Call options'!C50 -> 300 | H54: ='Call options'!D50 -> 1.65 | I54: ='Call options'!O50 -> 800 | J54: ='Call options'!P50 -> 0.1 | L54: 49 | M54: =_xlfn.NORM.S.INV(RAND()) -> 1.1260839 | N54: =_xlfn.NORM.S.INV(RAND()) -> -0.26482596 | O54: =M54 -> 1.1260839 | P54: =($D$16 * M54) + (SQRT(1 - $D$16^2) * N54) -> 0.50011509 | Q54: =$C$12*EXP(($C$6-$C$15-0.5*$C$13^2)*$C$8+$C$13*SQRT($C$8)*O54) -> 249.99235 | R54: =$D$12*EXP(($C$6-$D$15-0.5*$D$13^2)*$C$8+$D$13*SQRT($C$8)*P54) -> 517.46154 | S54: =SUMPRODUCT(Q54:R54,$C$19:$D$19) -> 12453317 | T54: =MAX(S54-$C$7,0) -> 2453316.8 | U54: =T54-AE54 -> 2386554.3 | AA54: =Q54 -> 249.99235 | AB54: =R54 -> 517.46154 | AC54: =MAX(AA54-$X$10,0) -> 74.992349 | AD54: =MAX(AB54-$Y$10,0) -> 37.461545 | AE54: =T54-$AL$7-SUMPRODUCT($AH$17:$AK$17,AA54:AD54) -> 66762.509
G55: ='Call options'!C51 -> 310 | H55: ='Call options'!D51 -> 1.3 | L55: 50 | M55: =_xlfn.NORM.S.INV(RAND()) -> -0.98989507 | N55: =_xlfn.NORM.S.INV(RAND()) -> 1.1865018 | O55: =M55 -> -0.98989507 | P55: =($D$16 * M55) + (SQRT(1 - $D$16^2) * N55) -> 0.30311342 | Q55: =$C$12*EXP(($C$6-$C$15-0.5*$C$13^2)*$C$8+$C$13*SQRT($C$8)*O55) -> 120.90269 | R55: =$D$12*EXP(($C$6-$D$15-0.5*$D$13^2)*$C$8+$D$13*SQRT($C$8)*P55) -> 500.86165 | S55: =SUMPRODUCT(Q55:R55,$C$19:$D$19) -> 8649573.6 | T55: =MAX(S55-$C$7,0) -> 0 | U55: =T55-AE55 -> 122486.66 | AA55: =Q55 -> 120.90269 | AB55: =R55 -> 500.86165 | AC55: =MAX(AA55-$X$10,0) -> 0 | AD55: =MAX(AB55-$Y$10,0) -> 20.861649 | AE55: =T55-$AL$7-SUMPRODUCT($AH$17:$AK$17,AA55:AD55) -> -122486.66
G56: ='Call options'!C52 -> 320 | H56: ='Call options'!D52 -> 1.13 | L56: 51 | M56: =_xlfn.NORM.S.INV(RAND()) -> -0.37034199 | N56: =_xlfn.NORM.S.INV(RAND()) -> 0.31564273 | O56: =M56 -> -0.37034199 | P56: =($D$16 * M56) + (SQRT(1 - $D$16^2) * N56) -> 0.013517155 | Q56: =$C$12*EXP(($C$6-$C$15-0.5*$C$13^2)*$C$8+$C$13*SQRT($C$8)*O56) -> 149.5584 | R56: =$D$12*EXP(($C$6-$D$15-0.5*$D$13^2)*$C$8+$D$13*SQRT($C$8)*P56) -> 477.42138 | S56: =SUMPRODUCT(Q56:R56,$C$19:$D$19) -> 9209614.1 | T56: =MAX(S56-$C$7,0) -> 0 | U56: =T56-AE56 -> -121779.38 | AA56: =Q56 -> 149.5584 | AB56: =R56 -> 477.42138 | AC56: =MAX(AA56-$X$10,0) -> 0 | AD56: =MAX(AB56-$Y$10,0) -> 0 | AE56: =T56-$AL$7-SUMPRODUCT($AH$17:$AK$17,AA56:AD56) -> 121779.38
G57: ='Call options'!C53 -> 330 | H57: ='Call options'!D53 -> 0.99 | L57: 52 | M57: =_xlfn.NORM.S.INV(RAND()) -> 0.22075508 | N57: =_xlfn.NORM.S.INV(RAND()) -> 0.53395198 | O57: =M57 -> 0.22075508 | P57: =($D$16 * M57) + (SQRT(1 - $D$16^2) * N57) -> 0.55431531 | Q57: =$C$12*EXP(($C$6-$C$15-0.5*$C$13^2)*$C$8+$C$13*SQRT($C$8)*O57) -> 183.20736 | R57: =$D$12*EXP(($C$6-$D$15-0.5*$D$13^2)*$C$8+$D$13*SQRT($C$8)*P57) -> 522.12435 | S57: =SUMPRODUCT(Q57:R57,$C$19:$D$19) -> 10624332 | T57: =MAX(S57-$C$7,0) -> 624331.95 | U57: =T57-AE57 -> 514807.71 | AA57: =Q57 -> 183.20736 | AB57: =R57 -> 522.12435 | AC57: =MAX(AA57-$X$10,0) -> 8.2073605 | AD57: =MAX(AB57-$Y$10,0) -> 42.124345 | AE57: =T57-$AL$7-SUMPRODUCT($AH$17:$AK$17,AA57:AD57) -> 109524.24
G58: ='Call options'!C54 -> 340 | H58: ='Call options'!D54 -> 0.86 | L58: 53 | M58: =_xlfn.NORM.S.INV(RAND()) -> -0.6783451 | N58: =_xlfn.NORM.S.INV(RAND()) -> 2.7290109 | O58: =M58 -> -0.6783451 | P58: =($D$16 * M58) + (SQRT(1 - $D$16^2) * N58) -> 1.699846 | Q58: =$C$12*EXP(($C$6-$C$15-0.5*$C$13^2)*$C$8+$C$13*SQRT($C$8)*O58) -> 134.55127 | R58: =$D$12*EXP(($C$6-$D$15-0.5*$D$13^2)*$C$8+$D$13*SQRT($C$8)*P58) -> 631.12248 | S58: =SUMPRODUCT(Q58:R58,$C$19:$D$19) -> 10398739 | T58: =MAX(S58-$C$7,0) -> 398738.51 | U58: =T58-AE58 -> 1436157.6 | AA58: =Q58 -> 134.55127 | AB58: =R58 -> 631.12248 | AC58: =MAX(AA58-$X$10,0) -> 0 | AD58: =MAX(AB58-$Y$10,0) -> 151.12248 | AE58: =T58-$AL$7-SUMPRODUCT($AH$17:$AK$17,AA58:AD58) -> -1037419.1
G59: ='Call options'!C55 -> 350 | H59: ='Call options'!D55 -> 0.71 | L59: 54 | M59: =_xlfn.NORM.S.INV(RAND()) -> 1.0846686 | N59: =_xlfn.NORM.S.INV(RAND()) -> 0.32376194 | O59: =M59 -> 1.0846686 | P59: =($D$16 * M59) + (SQRT(1 - $D$16^2) * N59) -> 0.93252858 | Q59: =$C$12*EXP(($C$6-$C$15-0.5*$C$13^2)*$C$8+$C$13*SQRT($C$8)*O59) -> 246.463 | R59: =$D$12*EXP(($C$6-$D$15-0.5*$D$13^2)*$C$8+$D$13*SQRT($C$8)*P59) -> 555.85251 | S59: =SUMPRODUCT(Q59:R59,$C$19:$D$19) -> 12756493 | T59: =MAX(S59-$C$7,0) -> 2756492.7 | U59: =T59-AE59 -> 2676791.8 | AA59: =Q59 -> 246.463 | AB59: =R59 -> 555.85251 | AC59: =MAX(AA59-$X$10,0) -> 71.463001 | AD59: =MAX(AB59-$Y$10,0) -> 75.85251 | AE59: =T59-$AL$7-SUMPRODUCT($AH$17:$AK$17,AA59:AD59) -> 79700.852
G60: ='Call options'!C56 -> 360 | H60: ='Call options'!D56 -> 0.62 | L60: 55 | M60: =_xlfn.NORM.S.INV(RAND()) -> 1.6599886 | N60: =_xlfn.NORM.S.INV(RAND()) -> -0.016748258 | O60: =M60 -> 1.6599886 | P60: =($D$16 * M60) + (SQRT(1 - $D$16^2) * N60) -> 1.0282217 | Q60: =$C$12*EXP(($C$6-$C$15-0.5*$C$13^2)*$C$8+$C$13*SQRT($C$8)*O60) -> 300.2835 | R60: =$D$12*EXP(($C$6-$D$15-0.5*$D$13^2)*$C$8+$D$13*SQRT($C$8)*P60) -> 564.72616 | S60: =SUMPRODUCT(Q60:R60,$C$19:$D$19) -> 14362831 | T60: =MAX(S60-$C$7,0) -> 4362831.1 | U60: =T60-AE60 -> 4314054.9 | AA60: =Q60 -> 300.2835 | AB60: =R60 -> 564.72616 | AC60: =MAX(AA60-$X$10,0) -> 125.2835 | AD60: =MAX(AB60-$Y$10,0) -> 84.726159 | AE60: =T60-$AL$7-SUMPRODUCT($AH$17:$AK$17,AA60:AD60) -> 48776.265
G61: ='Call options'!C57 -> 370 | H61: ='Call options'!D57 -> 0.47 | L61: 56 | M61: =_xlfn.NORM.S.INV(RAND()) -> -1.0895321 | N61: =_xlfn.NORM.S.INV(RAND()) -> 0.10875195 | O61: =M61 -> -1.0895321 | P61: =($D$16 * M61) + (SQRT(1 - $D$16^2) * N61) -> -0.59873756 | Q61: =$C$12*EXP(($C$6-$C$15-0.5*$C$13^2)*$C$8+$C$13*SQRT($C$8)*O61) -> 116.83693 | R61: =$D$12*EXP(($C$6-$D$15-0.5*$D$13^2)*$C$8+$D$13*SQRT($C$8)*P61) -> 431.41332 | S61: =SUMPRODUCT(Q61:R61,$C$19:$D$19) -> 7807295.3 | T61: =MAX(S61-$C$7,0) -> 0 | U61: =T61-AE61 -> -74539.808 | AA61: =Q61 -> 116.83693 | AB61: =R61 -> 431.41332 | AC61: =MAX(AA61-$X$10,0) -> 0 | AD61: =MAX(AB61-$Y$10,0) -> 0 | AE61: =T61-$AL$7-SUMPRODUCT($AH$17:$AK$17,AA61:AD61) -> 74539.808
G62: ='Call options'!C58 -> 380 | H62: ='Call options'!D58 -> 0.33 | L62: 57 | M62: =_xlfn.NORM.S.INV(RAND()) -> 0.60531182 | N62: =_xlfn.NORM.S.INV(RAND()) -> 1.7395546 | O62: =M62 -> 0.60531182 | P62: =($D$16 * M62) + (SQRT(1 - $D$16^2) * N62) -> 1.7344603 | Q62: =$C$12*EXP(($C$6-$C$15-0.5*$C$13^2)*$C$8+$C$13*SQRT($C$8)*O62) -> 209.06437 | R62: =$D$12*EXP(($C$6-$D$15-0.5*$D$13^2)*$C$8+$D$13*SQRT($C$8)*P62) -> 634.74852 | S62: =SUMPRODUCT(Q62:R62,$C$19:$D$19) -> 12531906 | T62: =MAX(S62-$C$7,0) -> 2531905.9 | U62: =T62-AE62 -> 2406903.1 | AA62: =Q62 -> 209.06437 | AB62: =R62 -> 634.74852 | AC62: =MAX(AA62-$X$10,0) -> 34.064366 | AD62: =MAX(AB62-$Y$10,0) -> 154.74852 | AE62: =T62-$AL$7-SUMPRODUCT($AH$17:$AK$17,AA62:AD62) -> 125002.71
G63: ='Call options'!C59 -> 390 | H63: ='Call options'!D59 -> 0.37 | L63: 58 | M63: =_xlfn.NORM.S.INV(RAND()) -> 0.05476264 | N63: =_xlfn.NORM.S.INV(RAND()) -> 0.40133321 | O63: =M63 -> 0.05476264 | P63: =($D$16 * M63) + (SQRT(1 - $D$16^2) * N63) -> 0.34690933 | Q63: =$C$12*EXP(($C$6-$C$15-0.5*$C$13^2)*$C$8+$C$13*SQRT($C$8)*O63) -> 173.05876 | R63: =$D$12*EXP(($C$6-$D$15-0.5*$D$13^2)*$C$8+$D$13*SQRT($C$8)*P63) -> 504.50537 | S63: =SUMPRODUCT(Q63:R63,$C$19:$D$19) -> 10154291 | T63: =MAX(S63-$C$7,0) -> 154291.36 | U63: =T63-AE63 -> 101358.72 | AA63: =Q63 -> 173.05876 | AB63: =R63 -> 504.50537 | AC63: =MAX(AA63-$X$10,0) -> 0 | AD63: =MAX(AB63-$Y$10,0) -> 24.505366 | AE63: =T63-$AL$7-SUMPRODUCT($AH$17:$AK$17,AA63:AD63) -> 52932.637
G64: ='Call options'!C60 -> 400 | H64: ='Call options'!D60 -> 0.33 | L64: 59 | M64: =_xlfn.NORM.S.INV(RAND()) -> -0.23872823 | N64: =_xlfn.NORM.S.INV(RAND()) -> 0.15868688 | O64: =M64 -> -0.23872823 | P64: =($D$16 * M64) + (SQRT(1 - $D$16^2) * N64) -> -0.026162345 | Q64: =$C$12*EXP(($C$6-$C$15-0.5*$C$13^2)*$C$8+$C$13*SQRT($C$8)*O64) -> 156.47117 | R64: =$D$12*EXP(($C$6-$D$15-0.5*$D$13^2)*$C$8+$D$13*SQRT($C$8)*P64) -> 474.2963 | S64: =SUMPRODUCT(Q64:R64,$C$19:$D$19) -> 9371230.1 | T64: =MAX(S64-$C$7,0) -> 0 | U64: =T64-AE64 -> -128782.38 | AA64: =Q64 -> 156.47117 | AB64: =R64 -> 474.2963 | AC64: =MAX(AA64-$X$10,0) -> 0 | AD64: =MAX(AB64-$Y$10,0) -> 0 | AE64: =T64-$AL$7-SUMPRODUCT($AH$17:$AK$17,AA64:AD64) -> 128782.38
G65: ='Call options'!C61 -> 410 | H65: ='Call options'!D61 -> 0.26 | L65: 60 | M65: =_xlfn.NORM.S.INV(RAND()) -> -0.14129855 | N65: =_xlfn.NORM.S.INV(RAND()) -> 0.28396217 | O65: =M65 -> -0.14129855 | P65: =($D$16 * M65) + (SQRT(1 - $D$16^2) * N65) -> 0.132517 | Q65: =$C$12*EXP(($C$6-$C$15-0.5*$C$13^2)*$C$8+$C$13*SQRT($C$8)*O65) -> 161.79348 | R65: =$D$12*EXP(($C$6-$D$15-0.5*$D$13^2)*$C$8+$D$13*SQRT($C$8)*P65) -> 486.91759 | S65: =SUMPRODUCT(Q65:R65,$C$19:$D$19) -> 9653179.2 | T65: =MAX(S65-$C$7,0) -> 0 | U65: =T65-AE65 -> -65480.072 | AA65: =Q65 -> 161.79348 | AB65: =R65 -> 486.91759 | AC65: =MAX(AA65-$X$10,0) -> 0 | AD65: =MAX(AB65-$Y$10,0) -> 6.9175887 | AE65: =T65-$AL$7-SUMPRODUCT($AH$17:$AK$17,AA65:AD65) -> 65480.072
G66: ='Call options'!C62 -> 420 | H66: ='Call options'!D62 -> 0.27 | L66: 61 | M66: =_xlfn.NORM.S.INV(RAND()) -> 0.44449204 | N66: =_xlfn.NORM.S.INV(RAND()) -> -0.52468189 | O66: =M66 -> 0.44449204 | P66: =($D$16 * M66) + (SQRT(1 - $D$16^2) * N66) -> -0.12980453 | Q66: =$C$12*EXP(($C$6-$C$15-0.5*$C$13^2)*$C$8+$C$13*SQRT($C$8)*O66) -> 197.83445 | R66: =$D$12*EXP(($C$6-$D$15-0.5*$D$13^2)*$C$8+$D$13*SQRT($C$8)*P66) -> 466.2298 | S66: =SUMPRODUCT(Q66:R66,$C$19:$D$19) -> 10449730 | T66: =MAX(S66-$C$7,0) -> 449729.79 | U66: =T66-AE66 -> 508608.49 | AA66: =Q66 -> 197.83445 | AB66: =R66 -> 466.2298 | AC66: =MAX(AA66-$X$10,0) -> 22.834449 | AD66: =MAX(AB66-$Y$10,0) -> 0 | AE66: =T66-$AL$7-SUMPRODUCT($AH$17:$AK$17,AA66:AD66) -> -58878.705
L67: 62 | M67: =_xlfn.NORM.S.INV(RAND()) -> 1.117586 | N67: =_xlfn.NORM.S.INV(RAND()) -> 0.99115855 | O67: =M67 -> 1.117586 | P67: =($D$16 * M67) + (SQRT(1 - $D$16^2) * N67) -> 1.4729451 | Q67: =$C$12*EXP(($C$6-$C$15-0.5*$C$13^2)*$C$8+$C$13*SQRT($C$8)*O67) -> 249.26407 | R67: =$D$12*EXP(($C$6-$D$15-0.5*$D$13^2)*$C$8+$D$13*SQRT($C$8)*P67) -> 607.86092 | S67: =SUMPRODUCT(Q67:R67,$C$19:$D$19) -> 13380405 | T67: =MAX(S67-$C$7,0) -> 3380405.4 | U67: =T67-AE67 -> 3287883.5 | AA67: =Q67 -> 249.26407 | AB67: =R67 -> 607.86092 | AC67: =MAX(AA67-$X$10,0) -> 74.264073 | AD67: =MAX(AB67-$Y$10,0) -> 127.86092 | AE67: =T67-$AL$7-SUMPRODUCT($AH$17:$AK$17,AA67:AD67) -> 92521.816
L68: 63 | M68: =_xlfn.NORM.S.INV(RAND()) -> 1.0401627 | N68: =_xlfn.NORM.S.INV(RAND()) -> -0.015935976 | O68: =M68 -> 1.0401627 | P68: =($D$16 * M68) + (SQRT(1 - $D$16^2) * N68) -> 0.64005456 | Q68: =$C$12*EXP(($C$6-$C$15-0.5*$C$13^2)*$C$8+$C$13*SQRT($C$8)*O68) -> 242.7258 | R68: =$D$12*EXP(($C$6-$D$15-0.5*$D$13^2)*$C$8+$D$13*SQRT($C$8)*P68) -> 529.58637 | S68: =SUMPRODUCT(Q68:R68,$C$19:$D$19) -> 12376088 | T68: =MAX(S68-$C$7,0) -> 2376088.3 | U68: =T68-AE68 -> 2301420.8 | AA68: =Q68 -> 242.7258 | AB68: =R68 -> 529.58637 | AC68: =MAX(AA68-$X$10,0) -> 67.725797 | AD68: =MAX(AB68-$Y$10,0) -> 49.586375 | AE68: =T68-$AL$7-SUMPRODUCT($AH$17:$AK$17,AA68:AD68) -> 74667.515
L69: 64 | M69: =_xlfn.NORM.S.INV(RAND()) -> -0.15443291 | N69: =_xlfn.NORM.S.INV(RAND()) -> -0.89705319 | O69: =M69 -> -0.15443291 | P69: =($D$16 * M69) + (SQRT(1 - $D$16^2) * N69) -> -0.7954964 | Q69: =$C$12*EXP(($C$6-$C$15-0.5*$C$13^2)*$C$8+$C$13*SQRT($C$8)*O69) -> 161.06556 | R69: =$D$12*EXP(($C$6-$D$15-0.5*$D$13^2)*$C$8+$D$13*SQRT($C$8)*P69) -> 417.59059 | S69: =SUMPRODUCT(Q69:R69,$C$19:$D$19) -> 8906026 | T69: =MAX(S69-$C$7,0) -> 0 | U69: =T69-AE69 -> -120776.12 | AA69: =Q69 -> 161.06556 | AB69: =R69 -> 417.59059 | AC69: =MAX(AA69-$X$10,0) -> 0 | AD69: =MAX(AB69-$Y$10,0) -> 0 | AE69: =T69-$AL$7-SUMPRODUCT($AH$17:$AK$17,AA69:AD69) -> 120776.12
L70: 65 | M70: =_xlfn.NORM.S.INV(RAND()) -> 0.95241751 | N70: =_xlfn.NORM.S.INV(RAND()) -> 1.3459197 | O70: =M70 -> 0.95241751 | P70: =($D$16 * M70) + (SQRT(1 - $D$16^2) * N70) -> 1.6456274 | Q70: =$C$12*EXP(($C$6-$C$15-0.5*$C$13^2)*$C$8+$C$13*SQRT($C$8)*O70) -> 235.52293 | R70: =$D$12*EXP(($C$6-$D$15-0.5*$D$13^2)*$C$8+$D$13*SQRT($C$8)*P70) -> 625.48438 | S70: =SUMPRODUCT(Q70:R70,$C$19:$D$19) -> 13178761 | T70: =MAX(S70-$C$7,0) -> 3178761 | U70: =T70-AE70 -> 3072775.8 | AA70: =Q70 -> 235.52293 | AB70: =R70 -> 625.48438 | AC70: =MAX(AA70-$X$10,0) -> 60.52293 | AD70: =MAX(AB70-$Y$10,0) -> 145.48438 | AE70: =T70-$AL$7-SUMPRODUCT($AH$17:$AK$17,AA70:AD70) -> 105985.22
L71: 66 | M71: =_xlfn.NORM.S.INV(RAND()) -> -1.1829669 | N71: =_xlfn.NORM.S.INV(RAND()) -> 0.96634348 | O71: =M71 -> -1.1829669 | P71: =($D$16 * M71) + (SQRT(1 - $D$16^2) * N71) -> 0.010545486 | Q71: =$C$12*EXP(($C$6-$C$15-0.5*$C$13^2)*$C$8+$C$13*SQRT($C$8)*O71) -> 113.14858 | R71: =$D$12*EXP(($C$6-$D$15-0.5*$D$13^2)*$C$8+$D$13*SQRT($C$8)*P71) -> 477.18662 | S71: =SUMPRODUCT(Q71:R71,$C$19:$D$19) -> 8183381.9 | T71: =MAX(S71-$C$7,0) -> 0 | U71: =T71-AE71 -> -81025.186 | AA71: =Q71 -> 113.14858 | AB71: =R71 -> 477.18662 | AC71: =MAX(AA71-$X$10,0) -> 0 | AD71: =MAX(AB71-$Y$10,0) -> 0 | AE71: =T71-$AL$7-SUMPRODUCT($AH$17:$AK$17,AA71:AD71) -> 81025.186
L72: 67 | M72: =_xlfn.NORM.S.INV(RAND()) -> -0.091477121 | N72: =_xlfn.NORM.S.INV(RAND()) -> 1.5327525 | O72: =M72 -> -0.091477121 | P72: =($D$16 * M72) + (SQRT(1 - $D$16^2) * N72) -> 1.1363263 | Q72: =$C$12*EXP(($C$6-$C$15-0.5*$C$13^2)*$C$8+$C$13*SQRT($C$8)*O72) -> 164.58466 | R72: =$D$12*EXP(($C$6-$D$15-0.5*$D$13^2)*$C$8+$D$13*SQRT($C$8)*P72) -> 574.92125 | S72: =SUMPRODUCT(Q72:R72,$C$19:$D$19) -> 10654116 | T72: =MAX(S72-$C$7,0) -> 654116 | U72: =T72-AE72 -> 829217.75 | AA72: =Q72 -> 164.58466 | AB72: =R72 -> 574.92125 | AC72: =MAX(AA72-$X$10,0) -> 0 | AD72: =MAX(AB72-$Y$10,0) -> 94.921255 | AE72: =T72-$AL$7-SUMPRODUCT($AH$17:$AK$17,AA72:AD72) -> -175101.75
L73: 68 | M73: =_xlfn.NORM.S.INV(RAND()) -> 0.055512135 | N73: =_xlfn.NORM.S.INV(RAND()) -> -1.5451533 | O73: =M73 -> 0.055512135 | P73: =($D$16 * M73) + (SQRT(1 - $D$16^2) * N73) -> -1.1685439 | Q73: =$C$12*EXP(($C$6-$C$15-0.5*$C$13^2)*$C$8+$C$13*SQRT($C$8)*O73) -> 173.10329 | R73: =$D$12*EXP(($C$6-$D$15-0.5*$D$13^2)*$C$8+$D$13*SQRT($C$8)*P73) -> 392.58742 | S73: =SUMPRODUCT(Q73:R73,$C$19:$D$19) -> 8982419.7 | T73: =MAX(S73-$C$7,0) -> 0 | U73: =T73-AE73 -> -128437.52 | AA73: =Q73 -> 173.10329 | AB73: =R73 -> 392.58742 | AC73: =MAX(AA73-$X$10,0) -> 0 | AD73: =MAX(AB73-$Y$10,0) -> 0 | AE73: =T73-$AL$7-SUMPRODUCT($AH$17:$AK$17,AA73:AD73) -> 128437.52
L74: 69 | M74: =_xlfn.NORM.S.INV(RAND()) -> 0.5826491 | N74: =_xlfn.NORM.S.INV(RAND()) -> -0.36532368 | O74: =M74 -> 0.5826491 | P74: =($D$16 * M74) + (SQRT(1 - $D$16^2) * N74) -> 0.080965748 | Q74: =$C$12*EXP(($C$6-$C$15-0.5*$C$13^2)*$C$8+$C$13*SQRT($C$8)*O74) -> 207.44407 | R74: =$D$12*EXP(($C$6-$D$15-0.5*$D$13^2)*$C$8+$D$13*SQRT($C$8)*P74) -> 482.78082 | S74: =SUMPRODUCT(Q74:R74,$C$19:$D$19) -> 10893421 | T74: =MAX(S74-$C$7,0) -> 893420.86 | U74: =T74-AE74 -> 809955.6 | AA74: =Q74 -> 207.44407 | AB74: =R74 -> 482.78082 | AC74: =MAX(AA74-$X$10,0) -> 32.444069 | AD74: =MAX(AB74-$Y$10,0) -> 2.780817 | AE74: =T74-$AL$7-SUMPRODUCT($AH$17:$AK$17,AA74:AD74) -> 83465.259
L75: 70 | M75: =_xlfn.NORM.S.INV(RAND()) -> 1.1169016 | N75: =_xlfn.NORM.S.INV(RAND()) -> -0.62223834 | O75: =M75 -> 1.1169016 | P75: =($D$16 * M75) + (SQRT(1 - $D$16^2) * N75) -> 0.21600259 | Q75: =$C$12*EXP(($C$6-$C$15-0.5*$C$13^2)*$C$8+$C$13*SQRT($C$8)*O75) -> 249.20551 | R75: =$D$12*EXP(($C$6-$D$15-0.5*$D$13^2)*$C$8+$D$13*SQRT($C$8)*P75) -> 493.69227 | S75: =SUMPRODUCT(Q75:R75,$C$19:$D$19) -> 12182043 | T75: =MAX(S75-$C$7,0) -> 2182043 | U75: =T75-AE75 -> 2121446.3 | AA75: =Q75 -> 249.20551 | AB75: =R75 -> 493.69227 | AC75: =MAX(AA75-$X$10,0) -> 74.205513 | AD75: =MAX(AB75-$Y$10,0) -> 13.692274 | AE75: =T75-$AL$7-SUMPRODUCT($AH$17:$AK$17,AA75:AD75) -> 60596.744
L76: 71 | M76: =_xlfn.NORM.S.INV(RAND()) -> -0.42910796 | N76: =_xlfn.NORM.S.INV(RAND()) -> -0.20477096 | O76: =M76 -> -0.42910796 | P76: =($D$16 * M76) + (SQRT(1 - $D$16^2) * N76) -> -0.42864322 | Q76: =$C$12*EXP(($C$6-$C$15-0.5*$C$13^2)*$C$8+$C$13*SQRT($C$8)*O76) -> 146.57127 | R76: =$D$12*EXP(($C$6-$D$15-0.5*$D$13^2)*$C$8+$D$13*SQRT($C$8)*P76) -> 443.731 | S76: =SUMPRODUCT(Q76:R76,$C$19:$D$19) -> 8772479.5 | T76: =MAX(S76-$C$7,0) -> 0 | U76: =T76-AE76 -> -110632.29 | AA76: =Q76 -> 146.57127 | AB76: =R76 -> 443.731 | AC76: =MAX(AA76-$X$10,0) -> 0 | AD76: =MAX(AB76-$Y$10,0) -> 0 | AE76: =T76-$AL$7-SUMPRODUCT($AH$17:$AK$17,AA76:AD76) -> 110632.29
L77: 72 | M77: =_xlfn.NORM.S.INV(RAND()) -> -1.7339774 | N77: =_xlfn.NORM.S.INV(RAND()) -> 1.7920163 | O77: =M77 -> -1.7339774 | P77: =($D$16 * M77) + (SQRT(1 - $D$16^2) * N77) -> 0.30794561 | Q77: =$C$12*EXP(($C$6-$C$15-0.5*$C$13^2)*$C$8+$C$13*SQRT($C$8)*O77) -> 93.647002 | R77: =$D$12*EXP(($C$6-$D$15-0.5*$D$13^2)*$C$8+$D$13*SQRT($C$8)*P77) -> 501.26238 | S77: =SUMPRODUCT(Q77:R77,$C$19:$D$19) -> 7887398.7 | T77: =MAX(S77-$C$7,0) -> 0 | U77: =T77-AE77 -> 157042.01 | AA77: =Q77 -> 93.647002 | AB77: =R77 -> 501.26238 | AC77: =MAX(AA77-$X$10,0) -> 0 | AD77: =MAX(AB77-$Y$10,0) -> 21.26238 | AE77: =T77-$AL$7-SUMPRODUCT($AH$17:$AK$17,AA77:AD77) -> -157042.01
L78: 73 | M78: =_xlfn.NORM.S.INV(RAND()) -> 0.0011411067 | N78: =_xlfn.NORM.S.INV(RAND()) -> -0.15735167 | O78: =M78 -> 0.0011411067 | P78: =($D$16 * M78) + (SQRT(1 - $D$16^2) * N78) -> -0.12182967 | Q78: =$C$12*EXP(($C$6-$C$15-0.5*$C$13^2)*$C$8+$C$13*SQRT($C$8)*O78) -> 169.90206 | R78: =$D$12*EXP(($C$6-$D$15-0.5*$D$13^2)*$C$8+$D$13*SQRT($C$8)*P78) -> 466.84558 | S78: =SUMPRODUCT(Q78:R78,$C$19:$D$19) -> 9670781.6 | T78: =MAX(S78-$C$7,0) -> 0 | U78: =T78-AE78 -> -142069 | AA78: =Q78 -> 169.90206 | AB78: =R78 -> 466.84558 | AC78: =MAX(AA78-$X$10,0) -> 0 | AD78: =MAX(AB78-$Y$10,0) -> 0 | AE78: =T78-$AL$7-SUMPRODUCT($AH$17:$AK$17,AA78:AD78) -> 142069
... L10005: 10000 | M10005: =_xlfn.NORM.S.INV(RAND()) -> -0.86219069 | N10005: =_xlfn.NORM.S.INV(RAND()) -> -0.21014836 | O10005: =M10005 -> -0.86219069 | P10005: =($D$16 * M10005) + (SQRT(1 - $D$16^2) * N10005) -> -0.70449204 | Q10005: =$C$12*EXP(($C$6-$C$15-0.5*$C$13^2)*$C$8+$C$13*SQRT($C$8)*O10005) -> 126.3213 | R10005: =$D$12*EXP(($C$6-$D$15-0.5*$D$13^2)*$C$8+$D$13*SQRT($C$8)*P10005) -> 423.92791 | S10005: =SUMPRODUCT(Q10005:R10005,$C$19:$D$19) -> 7995514.6 | T10005: =MAX(S10005-$C$7,0) -> 0 | U10005: =T10005-AE10005 -> -83406.859 | AA10005: =Q10005 -> 126.3213 | AB10005: =R10005 -> 423.92791 | AC10005: =MAX(AA10005-$X$10,0) -> 0 | AD10005: =MAX(AB10005-$Y$10,0) -> 0 | AE10005: =T10005-$AL$7-SUMPRODUCT($AH$17:$AK$17,AA10005:AD10005) -> 83406.859

Sheet 3D
A3: Sum of Basket Call | B3: Column Labels
A4: Row Labels | B4: 255-260 | C4: 280-285 | D4: 285-290 | E4: 290-295 | F4: 295-300 | G4: 310-315 | H4: 315-320 | I4: 320-325 | J4: 325-330 | K4: 330-335 | L4: 335-340 | M4: 340-345 | N4: 345-350 | O4: 350-355 | P4: 355-360 | Q4: 360-365 | R4: 365-370 | S4: 370-375 | T4: 375-380 | U4: 380-385 | V4: 385-390 | W4: 390-395 | X4: 395-400 | Y4: 400-405 | Z4: 405-410 | AA4: 410-415 | AB4: 415-420 | AC4: 420-425 | AD4: 425-430 | AE4: 430-435 | AF4: 435-440 | AG4: 440-445 | AH4: 445-450 | AI4: 450-455 | AJ4: 455-460 | AK4: 460-465 | AL4: 465-470 | AM4: 470-475 | AN4: 475-480 | AO4: 480-485 | AP4: 485-490 | AQ4: 490-495 | AR4: 495-500 | AS4: 500-505 | AT4: 505-510 | AU4: 510-515 | AV4: 515-520 | AW4: 520-525 | AX4: 525-530 | AY4: 530-535 | AZ4: 535-540 | BA4: 540-545 | BB4: 545-550 | BC4: 550-555 | BD4: 555-560 | BE4: 560-565 | BF4: 565-570 | BG4: 570-575 | BH4: 575-580 | BI4: 580-585 | BJ4: 585-590 | BK4: 590-595 | BL4: 595-600 | BM4: 600-605 | BN4: 605-610 | BO4: 610-615 | BP4: 615-620 | BQ4: 620-625 | BR4: 625-630 | BS4: 630-635 | BT4: 635-640 | BU4: 640-645 | BV4: 645-650 | BW4: 650-655 | BX4: 655-660 | BY4: 660-665 | BZ4: 665-670 | CA4: 670-675 | CB4: 675-680 | CC4: 680-685 | CD4: 685-690 | CE4: 690-695 | CF4: 695-700 | CG4: 700-705 | CH4: 705-710 | CI4: 710-715 | CJ4: 715-720 | CK4: 720-725 | CL4: 725-730 | CM4: 735-740 | CN4: 740-745 | CO4: 745-750 | CP4: 765-770 | CQ4: 795-800 | CR4: Grand Total
A5: 55-60 | S5: 0 | T5: 0 | U5: 0 | CR5: 0
A6: 65-70 | D6: 0 | E6: 0 | H6: 0 | V6: 0 | Y6: 0 | AD6: 0 | AJ6: 0 | CR6: 0
A7: 70-75 | B7: 0 | F7: 0 | K7: 0 | M7: 0 | O7: 0 | S7: 0 | W7: 0 | X7: 0 | CR7: 0
A8: 75-80 | E8: 0 | H8: 0 | J8: 0 | K8: 0 | T8: 0 | X8: 0 | Y8: 0 | AC8: 0 | AE8: 0 | CR8: 0
A9: 80-85 | L9: 0 | O9: 0 | P9: 0 | R9: 0 | U9: 0 | V9: 0 | Y9: 0 | AF9: 0 | AG9: 0 | AH9: 0 | CR9: 0
A10: 85-90 | H10: 0 | J10: 0 | R10: 0 | T10: 0 | W10: 0 | X10: 0 | Y10: 0 | Z10: 0 | AG10: 0 | AN10: 0 | AO10: 0 | BA10: 0 | CR10: 0
A11: 90-95 | C11: 0 | G11: 0 | I11: 0 | J11: 0 | L11: 0 | M11: 0 | P11: 0 | S11: 0 | T11: 0 | V11: 0 | W11: 0 | Y11: 0 | Z11: 0 | AA11: 0 | AB11: 0 | AD11: 0 | AF11: 0 | AI11: 0 | AL11: 0 | AN11: 0 | AQ11: 0 | AR11: 0 | AV11: 0 | AZ11: 0 | CR11: 0
A12: 95-100 | K12: 0 | N12: 0 | O12: 0 | Q12: 0 | U12: 0 | V12: 0 | W12: 0 | X12: 0 | Y12: 0 | Z12: 0 | AA12: 0 | AD12: 0 | AE12: 0 | AF12: 0 | AG12: 0 | AH12: 0 | AI12: 0 | AJ12: 0 | AK12: 0 | AP12: 0 | AQ12: 0 | AR12: 0 | CR12: 0
A13: 100-105 | H13: 0 | I13: 0 | K13: 0 | L13: 0 | M13: 0 | N13: 0 | P13: 0 | Q13: 0 | R13: 0 | S13: 0 | T13: 0 | U13: 0 | W13: 0 | Y13: 0 | Z13: 0 | AA13: 0 | AB13: 0 | AC13: 0 | AE13: 0 | AF13: 0 | AH13: 0 | AI13: 0 | AL13: 0 | AM13: 0 | AO13: 0 | AP13: 0 | AT13: 0 | AX13: 0 | AZ13: 0 | BB13: 0 | BE13: 0 | CR13: 0
A14: 105-110 | D14: 0 | I14: 0 | L14: 0 | O14: 0 | Q14: 0 | R14: 0 | S14: 0 | T14: 0 | U14: 0 | V14: 0 | W14: 0 | X14: 0 | Y14: 0 | Z14: 0 | AA14: 0 | AB14: 0 | AC14: 0 | AD14: 0 | AE14: 0 | AF14: 0 | AH14: 0 | AI14: 0 | AJ14: 0 | AK14: 0 | AM14: 0 | AP14: 0 | AQ14: 0 | AZ14: 0 | CR14: 0
A15: 110-115 | G15: 0 | H15: 0 | J15: 0 | L15: 0 | P15: 0 | Q15: 0 | R15: 0 | S15: 0 | U15: 0 | V15: 0 | W15: 0 | X15: 0 | Y15: 0 | Z15: 0 | AA15: 0 | AB15: 0 | AC15: 0 | AD15: 0 | AE15: 0 | AG15: 0 | AH15: 0 | AJ15: 0 | AL15: 0 | AM15: 0 | AN15: 0 | AO15: 0 | AQ15: 0 | AR15: 0 | AS15: 0 | BB15: 0 | CR15: 0
A16: 115-120 | M16: 0 | O16: 0 | P16: 0 | S16: 0 | U16: 0 | V16: 0 | W16: 0 | X16: 0 | Y16: 0 | Z16: 0 | AA16: 0 | AB16: 0 | AC16: 0 | AD16: 0 | AE16: 0 | AF16: 0 | AG16: 0 | AH16: 0 | AI16: 0 | AJ16: 0 | AK16: 0 | AM16: 0 | AP16: 0 | AQ16: 0 | AR16: 0 | AS16: 0 | AT16: 0 | AU16: 0 | AV16: 0 | AW16: 0 | AX16: 0 | AY16: 0 | AZ16: 0 | CR16: 0
A17: 120-125 | I17: 0 | L17: 0 | P17: 0 | Q17: 0 | R17: 0 | T17: 0 | U17: 0 | V17: 0 | W17: 0 | X17: 0 | Y17: 0 | Z17: 0 | AA17: 0 | AB17: 0 | AC17: 0 | AD17: 0 | AE17: 0 | AF17: 0 | AG17: 0 | AI17: 0 | AJ17: 0 | AK17: 0 | AL17: 0 | AM17: 0 | AN17: 0 | AO17: 0 | AR17: 0 | AT17: 0 | AU17: 0 | AW17: 0 | AY17: 0 | BC17: 0 | BD17: 0 | BE17: 0 | CR17: 0
A18: 125-130 | H18: 0 | I18: 0 | M18: 0 | O18: 0 | P18: 0 | R18: 0 | S18: 0 | T18: 0 | U18: 0 | V18: 0 | W18: 0 | X18: 0 | Y18: 0 | Z18: 0 | AA18: 0 | AB18: 0 | AC18: 0 | AD18: 0 | AE18: 0 | AF18: 0 | AG18: 0 | AJ18: 0 | AK18: 0 | AL18: 0 | AM18: 0 | AO18: 0 | AP18: 0 | AQ18: 0 | AR18: 0 | AU18: 0 | AV18: 0 | AY18: 0 | BA18: 0 | BB18: 0 | BG18: 0 | BL18: 0 | CR18: 0
A19: 130-135 | D19: 0 | G19: 0 | N19: 0 | P19: 0 | Q19: 0 | R19: 0 | S19: 0 | T19: 0 | V19: 0 | W19: 0 | X19: 0 | Y19: 0 | AA19: 0 | AB19: 0 | AC19: 0 | AD19: 0 | AE19: 0 | AF19: 0 | AG19: 0 | AH19: 0 | AI19: 0 | AJ19: 0 | AK19: 0 | AL19: 0 | AM19: 0 | AN19: 0 | AO19: 0 | AP19: 0 | AQ19: 0 | AR19: 0 | AS19: 0 | AT19: 0 | AU19: 0 | BA19: 0 | BC19: 0 | BD19: 0 | CR19: 0
A20: 135-140 | I20: 0 | L20: 0 | M20: 0 | P20: 0 | S20: 0 | U20: 0 | V20: 0 | W20: 0 | X20: 0 | Y20: 0 | AA20: 0 | AB20: 0 | AC20: 0 | AD20: 0 | AE20: 0 | AF20: 0 | AG20: 0 | AH20: 0 | AI20: 0 | AJ20: 0 | AK20: 0 | AL20: 0 | AM20: 0 | AN20: 0 | AO20: 0 | AQ20: 0 | AR20: 0 | AS20: 0 | AT20: 0 | AV20: 0 | AX20: 0 | AY20: 0 | AZ20: 0 | BF20: 0 | CR20: 0
A21: 140-145 | O21: 0 | R21: 0 | S21: 0 | V21: 0 | W21: 0 | X21: 0 | Y21: 0 | Z21: 0 | AA21: 0 | AB21: 0 | AC21: 0 | AD21: 0 | AF21: 0 | AG21: 0 | AH21: 0 | AJ21: 0 | AK21: 0 | AL21: 0 | AM21: 0 | AP21: 0 | AQ21: 0 | AS21: 0 | AT21: 0 | AU21: 0 | AV21: 0 | AW21: 0 | AY21: 0 | BA21: 0 | BC21: 0 | BF21: 0 | BH21: 5475.5751 | CR21: 5475.5751
A22: 145-150 | G22: 0 | O22: 0 | P22: 0 | U22: 0 | W22: 0 | X22: 0 | Z22: 0 | AA22: 0 | AB22: 0 | AC22: 0 | AE22: 0 | AF22: 0 | AG22: 0 | AH22: 0 | AI22: 0 | AJ22: 0 | AK22: 0 | AL22: 0 | AM22: 0 | AN22: 0 | AO22: 0 | AP22: 0 | AR22: 0 | AS22: 0 | AU22: 0 | AV22: 0 | AW22: 0 | AZ22: 0 | BB22: 0 | BD22: 57846.449 | BG22: 201647.86 | CR22: 259494.31
A23: 150-155 | N23: 0 | P23: 0 | S23: 0 | U23: 0 | V23: 0 | Y23: 0 | Z23: 0 | AB23: 0 | AC23: 0 | AD23: 0 | AE23: 0 | AF23: 0 | AG23: 0 | AH23: 0 | AI23: 0 | AK23: 0 | AL23: 0 | AM23: 0 | AN23: 0 | AO23: 0 | AQ23: 0 | AR23: 0 | AS23: 0 | AU23: 0 | AW23: 0 | AX23: 0 | AZ23: 0 | BA23: 32338.161 | BB23: 85789.11 | BD23: 174806.2 | BE23: 175418.93 | BH23: 316047.7 | BL23: 509026.14 | CR23: 1293426.2
A24: 155-160 | K24: 0 | M24: 0 | N24: 0 | O24: 0 | Q24: 0 | R24: 0 | W24: 0 | Y24: 0 | Z24: 0 | AA24: 0 | AB24: 0 | AC24: 0 | AD24: 0 | AE24: 0 | AF24: 0 | AH24: 0 | AI24: 0 | AJ24: 0 | AK24: 0 | AM24: 0 | AN24: 0 | AO24: 0 | AP24: 0 | AQ24: 0 | AR24: 0 | AS24: 0 | AT24: 0 | AU24: 0 | AV24: 0 | AW24: 0 | AY24: 59194.09 | AZ24: 26414.44 | BA24: 134785.47 | BC24: 155605.62 | BD24: 315488.56 | BE24: 412920.28 | BF24: 419551.68 | BG24: 484845.79 | BJ24: 602994.53 | BL24: 713042.07 | CR24: 3324842.5
A25: 160-165 | P25: 0 | S25: 0 | V25: 0 | W25: 0 | X25: 0 | Z25: 0 | AA25: 0 | AB25: 0 | AC25: 0 | AE25: 0 | AF25: 0 | AG25: 0 | AH25: 0 | AJ25: 0 | AK25: 0 | AL25: 0 | AM25: 0 | AN25: 0 | AP25: 0 | AQ25: 0 | AR25: 0 | AS25: 0 | AT25: 0 | AU25: 395.3666 | AV25: 115548.51 | AY25: 255003.24 | AZ25: 555555.11 | BB25: 293009.1 | BC25: 401971.77 | BD25: 432104.73 | BP25: 1007461 | CR25: 3061048.8
A26: 165-170 | J26: 0 | K26: 0 | S26: 0 | V26: 0 | W26: 0 | X26: 0 | Z26: 0 | AA26: 0 | AC26: 0 | AD26: 0 | AE26: 0 | AF26: 0 | AG26: 0 | AH26: 0 | AI26: 0 | AJ26: 0 | AL26: 0 | AM26: 0 | AN26: 0 | AO26: 0 | AP26: 0 | AQ26: 0 | AR26: 0 | AS26: 19459.642 | AT26: 40277.627 | AU26: 63915.152 | AV26: 107737.19 | AW26: 610076.81 | AX26: 616980.94 | AZ26: 638537.68 | BA26: 763861.33 | BB26: 1406336.6 | BD26: 1591659.4 | BE26: 574447.73 | BG26: 732195.65 | BH26: 782542.64 | BL26: 1008847.2 | BV26: 1466857.9 | CR26: 10423733
A27: 170-175 | V27: 0 | X27: 0 | Y27: 0 | AB27: 0 | AD27: 0 | AE27: 0 | AF27: 0 | AG27: 0 | AI27: 0 | AJ27: 0 | AK27: 0 | AL27: 0 | AM27: 0 | AN27: 0 | AP27: 46295.929 | AQ27: 187344.1 | AR27: 72842.512 | AS27: 230682.12 | AT27: 205665.23 | AV27: 279039.43 | AW27: 383384.09 | AX27: 1230725.3 | AY27: 415223.47 | AZ27: 1509153.9 | BD27: 669162.55 | BF27: 1597687 | BG27: 2490732.2 | BI27: 1890773.1 | BJ27: 2060533.1 | BK27: 2133927.6 | BO27: 2577098 | BZ27: 1878748.9 | CR27: 19859019
A28: 175-180 | P28: 0 | S28: 0 | T28: 0 | U28: 0 | Y28: 0 | AA28: 0 | AC28: 0 | AD28: 0 | AE28: 0 | AF28: 0 | AG28: 0 | AH28: 0 | AI28: 0 | AK28: 0 | AL28: 0 | AN28: 85155.706 | AO28: 175892.81 | AP28: 55700.939 | AQ28: 383007.4 | AR28: 268509.55 | AS28: 446579.44 | AT28: 925283.33 | AU28: 801912.27 | AV28: 468780.14 | AW28: 1520836.4 | AX28: 573243.96 | AY28: 1160098.1 | AZ28: 1169287.6 | BA28: 622825.98 | BB28: 798982.56 | BC28: 2398141.6 | BD28: 846494.79 | BH28: 1075297.9 | BJ28: 1190677.2 | BL28: 1321994.8 | BO28: 1403623.4 | BT28: 1716272.8 | CR28: 19408599
A29: 180-185 | M29: 0 | O29: 0 | T29: 0 | U29: 0 | V29: 0 | X29: 0 | Y29: 0 | Z29: 0 | AA29: 0 | AB29: 0 | AC29: 0 | AD29: 0 | AE29: 0 | AF29: 0 | AG29: 0 | AH29: 0 | AI29: 0 | AJ29: 0 | AL29: 0 | AM29: 249797.49 | AN29: 471769.03 | AO29: 242877.3 | AP29: 1123643.4 | AQ29: 1215365.7 | AR29: 787818.95 | AS29: 1139640.8 | AT29: 1958586.7 | AU29: 463062.95 | AV29: 1141332.2 | AW29: 1154702.1 | AY29: 2816119.5 | AZ29: 2380596.1 | BA29: 873820.34 | BD29: 994174.41 | BF29: 1004226.9 | BL29: 2809883.7 | BM29: 1456190.9 | BU29: 1847360.1 | BV29: 1857974.9 | CE29: 2407902.5 | CR29: 28396846
A30: 185-190 | M30: 0 | S30: 0 | X30: 0 | Y30: 0 | AA30: 0 | AB30: 0 | AC30: 0 | AD30: 0 | AE30: 0 | AH30: 52559.74 | AI30: 9507.3573 | AK30: 412542.11 | AL30: 346944.02 | AM30: 679580.24 | AN30: 330887 | AO30: 675366.31 | AP30: 2096789.5 | AQ30: 2212527.4 | AU30: 578075.49 | AW30: 1483636.7 | AX30: 2433856.6 | AY30: 5407830.6 | AZ30: 948617.89 | BB30: 2057698.9 | BF30: 2512088.5 | BI30: 1350925.7 | BK30: 2980979.2 | BP30: 1693552.2 | CR30: 28263965
A31: 190-195 | S31: 0 | AA31: 0 | AB31: 0 | AD31: 0 | AF31: 34929.828 | AH31: 313714.76 | AI31: 362264.28 | AK31: 249169.66 | AL31: 1012939.2 | AM31: 787161.43 | AN31: 1240441.4 | AO31: 930348.75 | AP31: 1191132.1 | AQ31: 1021120.7 | AR31: 2455289.2 | AS31: 1299555.8 | AT31: 2118800 | AU31: 1622158.4 | AV31: 818999.61 | AW31: 1767830 | AY31: 1024744.3 | AZ31: 4279048.3 | BA31: 1137754.1 | BC31: 2416085.2 | BD31: 2571128.8 | BE31: 2655463.8 | BF31: 1305479.4 | BH31: 1481027.9 | BI31: 1474223.6 | BJ31: 1615142.4 | CC31: 2612961.9 | CR31: 39798915
A32: 195-200 | S32: 0 | T32: 0 | Y32: 0 | AC32: 0 | AE32: 135534.13 | AH32: 452680.03 | AI32: 638914.18 | AJ32: 612610.43 | AK32: 417462.81 | AL32: 482625.22 | AM32: 562183.17 | AN32: 551825.4 | AO32: 1238378.5 | AQ32: 2997658.5 | AR32: 1509123.8 | AS32: 800586.55 | AT32: 4601223.5 | AU32: 1948426.8 | AX32: 1160762.1 | AY32: 1195342.5 | BA32: 1226708.5 | BD32: 1421398.3 | BG32: 1547377.8 | BH32: 1604073.8 | BJ32: 5112459.7 | BL32: 1766965.3 | BM32: 3603985.1 | BW32: 2348280.2 | CR32: 37936586
A33: 200-205 | W33: 0 | Z33: 29337.476 | AC33: 35698.833 | AF33: 259794.51 | AH33: 350907.1 | AI33: 1375038.6 | AJ33: 953108.61 | AK33: 476459.5 | AL33: 607548.05 | AN33: 2102425.6 | AO33: 703791.16 | AQ33: 894747.55 | AR33: 1872285.5 | AS33: 926464.83 | AU33: 1045474.7 | AV33: 1168443 | AW33: 1222157.1 | AY33: 2562887 | BA33: 1371850.7 | BB33: 4096168.5 | BC33: 1476345.1 | BE33: 3161837.3 | BF33: 1599572.9 | BG33: 1713207.6 | BJ33: 1844639.7 | BM33: 1976862.4 | BN33: 4244047.2 | BS33: 2354929.1 | BT33: 2403581.3 | BW33: 2461713.2 | CR33: 45291324
A34: 205-210 | X34: 79601.385 | AB34: 204280.94 | AC34: 493214.91 | AD34: 340545.3 | AE34: 628789.96 | AG34: 983215.9 | AI34: 651684.31 | AJ34: 1268055 | AK34: 1993539.2 | AL34: 815109.96 | AM34: 2344536 | AN34: 1718417.4 | AO34: 938011.08 | AP34: 1006650.7 | AQ34: 1952143 | AS34: 1136630.3 | AT34: 1193988.6 | AU34: 1268357.7 | AV34: 3829366.1 | AX34: 2786314.6 | AY34: 1377526.8 | BB34: 1612477.1 | BC34: 1677655.9 | BD34: 1663817.2 | BE34: 1659118.8 | BH34: 1878577.8 | BK34: 2034957.8 | BL34: 2158165.1 | BN34: 4388134.1 | BP34: 2250475.9 | BU34: 2553330.3 | BY34: 2751854.4 | CR34: 51638543
A35: 210-215 | R35: 0 | U35: 0 | AA35: 583707.66 | AF35: 1078599.9 | AG35: 566587.22 | AH35: 638514.21 | AJ35: 822060.21 | AL35: 926033.03 | AM35: 1874879.7 | AN35: 1948274.5 | AO35: 1064037.1 | AP35: 1070006.3 | AQ35: 1085591.7 | AR35: 3665249.4 | AS35: 2387566.7 | AU35: 1318632 | AV35: 4063319.9 | AW35: 1448641.2 | AZ35: 1566346.1 | BA35: 3270619 | BD35: 1773748.7 | BF35: 1965674.5 | BG35: 1932211.2 | BH35: 2088246.4 | BI35: 4273007.9 | BJ35: 4181565.5 | BK35: 4338527.4 | BN35: 2421729.4 | BO35: 2353592.1 | BP35: 2387863.9 | BS35: 2562834.8 | CR35: 59657668
A36: 215-220 | U36: 179782.64 | V36: 103675.84 | AA36: 480961.8 | AE36: 629765.96 | AF36: 688780.2 | AG36: 2162233.6 | AH36: 1650144.8 | AJ36: 942794.81 | AL36: 2090012.9 | AM36: 3033914.9 | AN36: 4493621.2 | AO36: 1186167.5 | AP36: 1185786 | AQ36: 3873678.7 | AR36: 2633706.3 | AS36: 1314729 | AT36: 1484508.5 | AV36: 1517719.5 | AW36: 3201168.9 | AX36: 6592432.1 | AY36: 5145148.9 | AZ36: 1823615 | BB36: 3827195.2 | BC36: 1876669.5 | BE36: 1946005.5 | BG36: 6442621.3 | BH36: 2178907.3 | BJ36: 2229138.7 | BK36: 2308915.5 | BP36: 2654709 | BU36: 2789426.8 | BV36: 2966605 | CD36: 3401728.5 | CR36: 79036271
A37: 220-225 | X37: 492853.39 | Y37: 501069.99 | AB37: 1330473.4 | AC37: 700452.79 | AD37: 702438.53 | AE37: 1505776.2 | AF37: 843270.76 | AK37: 1091235.4 | AL37: 1099823.5 | AM37: 1166300.2 | AN37: 2522811.9 | AO37: 1349809.3 | AP37: 1323576.9 | AR37: 3060484.2 | AS37: 4570125.6 | AT37: 1513764.8 | AV37: 1743850.7 | AW37: 5228554.9 | AX37: 3551112.7 | AY37: 3636931 | BA37: 1892348.4 | BE37: 4222751.6 | BG37: 2220522.1 | BH37: 2391995.6 | BM37: 2602662 | BO37: 2641127.9 | BS37: 2823654.7 | BU37: 2953205.7 | CR37: 59682984
A38: 225-230 | AB38: 783838.89 | AC38: 770939.41 | AD38: 932767.78 | AE38: 917849.68 | AF38: 940160.85 | AH38: 1013848.3 | AI38: 1137454.8 | AJ38: 2442708.8 | AK38: 1200737.3 | AQ38: 3178118.7 | AR38: 1668785.5 | AU38: 1767769.3 | AW38: 1867650.2 | AY38: 1982404.9 | AZ38: 4023022.3 | BB38: 2081792.3 | BD38: 2193707.6 | BE38: 2254109.5 | BF38: 2409655.2 | BG38: 2365199.6 | BH38: 2490421 | BJ38: 5162325.9 | BM38: 2647817.4 | BN38: 2732808.2 | BO38: 2809542.2 | BU38: 3185080.8 | BX38: 3308817.8 | CR38: 58269334
A39: 230-235 | R39: 436144.17 | T39: 523986.65 | AC39: 917064.56 | AK39: 1338714 | AM39: 1427468.2 | AN39: 4690058.5 | AO39: 3134455.8 | AP39: 3199340 | AQ39: 8468148.7 | AS39: 3702927.1 | AT39: 3665894.4 | AV39: 3908942.2 | AW39: 2058211.8 | AY39: 2074706.1 | BC39: 2301990.3 | BE39: 2471346.2 | BG39: 2531516.5 | BH39: 2610401.1 | BJ39: 2734303.2 | BT39: 3185951.7 | BW39: 3410717.2 | CK39: 4078322.5 | CR39: 62870611
A40: 235-240 | AG40: 1377413.5 | AJ40: 1494760.9 | AK40: 4659357.2 | AM40: 1716238.3 | AN40: 3443177.9 | AP40: 1742185 | AQ40: 1889031.5 | AS40: 5846001.5 | AT40: 1942151.3 | AU40: 2000393.2 | AV40: 2113763.5 | AW40: 2189421.7 | AZ40: 2355170.1 | BE40: 2640043 | BG40: 5282266.5 | BT40: 3380718.5 | CR40: 44072093
A41: 240-245 | AE41: 1348379.4 | AI41: 3150526.4 | AJ41: 1587891.1 | AK41: 1624742.8 | AN41: 1830631 | AO41: 1909059.7 | AP41: 1919709.4 | AQ41: 1924036.7 | AR41: 2068733.1 | AW41: 4635593.4 | AX41: 2419094.7 | AY41: 2360692.8 | BA41: 2491055.8 | BB41: 2533501 | BC41: 2608847.7 | BG41: 8479582.9 | BI41: 2941960.5 | BM41: 3091838 | BN41: 6351824.3 | BO41: 3230258.2 | BS41: 3476394 | BW41: 3649554 | BY41: 3808763.6 | CH41: 4213729.3 | CR41: 73656400
A42: 245-250 | AB42: 1395435.1 | AD42: 1460736.4 | AM42: 1927433.7 | AO42: 2035872.7 | AP42: 4083057.7 | AR42: 4365376.6 | AS42: 2157184.7 | AT42: 2213108.2 | AV42: 2371074.8 | AW42: 9682497.4 | AX42: 5069022.5 | BB42: 2639453.4 | BD42: 2864911.5 | BG42: 2888970.2 | BJ42: 3129348.2 | BP42: 3498853 | BR42: 3503275.3 | CE42: 4250047.8 | CF42: 4217870.3 | CR42: 63753529
A43: 250-255 | AI43: 3563605.6 | AJ43: 1930690.5 | AL43: 5909873.2 | AM43: 2035024.6 | AS43: 2334452.5 | AU43: 2431208.7 | AV43: 2541781.9 | AY43: 7968845.5 | AZ43: 2799994.8 | BA43: 5584020.2 | BC43: 5801151.4 | BD43: 9031799 | BF43: 9185780.6 | BI43: 6458607.3 | BJ43: 3292545.4 | BQ43: 3665016.4 | CB43: 4250616.8 | CC43: 4244045.7 | CG43: 4427945.9 | CL43: 4665062.6 | CR43: 92122069
A44: 255-260 | AM44: 4318316.3 | AO44: 2245891.6 | AY44: 2827166.3 | AZ44: 2914698.1 | BA44: 2887648 | BB44: 8917952.6 | BC44: 3116757.9 | BF44: 6358778.8 | BL44: 3461235.9 | BQ44: 3817224.5 | BR44: 3820773.5 | BV44: 4082352.7 | BY44: 4167498.6 | CI44: 4774773.7 | CP44: 5259129.3 | CQ44: 5618146.8 | CR44: 68588345
A45: 260-265 | AL45: 2287284.8 | AM45: 2354858.4 | AO45: 2472626.7 | AU45: 5551405.7 | AY45: 2884997.5 | BE45: 6486852.8 | BH45: 3499021.9 | BO45: 3798517.5 | BR45: 3927785.4 | BS45: 4064548.1 | BT45: 3997205.9 | BV45: 4253746.7 | BY45: 4272015.6 | CR45: 49850867
A46: 265-270 | AI46: 2213036.4 | AJ46: 2372809.9 | AL46: 2403330.6 | AT46: 2876990.7 | AW46: 5998406.1 | AX46: 2972726.3 | BA46: 6344428.2 | BD46: 6702289.9 | BG46: 7097303.2 | BN46: 3895934 | BO46: 3910553.7 | BQ46: 4062334.2 | BY46: 4436092.8 | CR46: 55286236
A47: 270-275 | AI47: 2373908.5 | AK47: 2569534.2 | AQ47: 2797843.6 | AV47: 3126419.5 | AX47: 3208901.7 | BB47: 3343322.4 | BC47: 6912302.4 | BE47: 3554699.8 | BG47: 7267410.5 | BH47: 3762528.6 | BI47: 3718153.7 | BK47: 3921013.3 | BU47: 4338426.4 | BY47: 4677075.2 | CA47: 4766556.9 | CR47: 60338097
A48: 275-280 | AE48: 2302644.5 | AF48: 2339910.4 | AG48: 4898072.4 | AR48: 6007967.6 | AV48: 3308592.9 | AY48: 3388173.6 | BC48: 3589627.9 | BD48: 3588228.4 | BG48: 3784529.3 | BH48: 3799249.7 | BL48: 4123979 | BR48: 4426746.2 | BT48: 4417297.8 | CR48: 49975020
A49: 280-285 | AC49: 2426403 | AK49: 2765469.2 | AO49: 3039405.9 | AQ49: 3186103.3 | AR49: 3100682.1 | AU49: 3312782.2 | BC49: 11179602 | BI49: 3989719.2 | BN49: 4288570.3 | BP49: 4378801.2 | CM49: 5668711.1 | CR49: 47336250
A50: 285-290 | Z50: 2420960.2 | AT50: 3333773.7 | AY50: 7223481.5 | BB50: 7498663.5 | BD50: 7870812.3 | BH50: 4152671.4 | BM50: 4452377.9 | BX50: 4918673.5 | BY50: 4978414.8 | CJ50: 5561048.1 | CR50: 52410877
A51: 290-295 | AI51: 2985698.6 | AN51: 3157352.2 | AO51: 6459993.1 | AQ51: 3365423.3 | AU51: 3612595.7 | AV51: 3619140 | AW51: 3714302.3 | AY51: 3777899.6 | BJ51: 4379120 | BK51: 4467244 | BN51: 4621482.2 | BP51: 4661502.1 | BR51: 4760088.9 | CE51: 5484577.1 | CR51: 59066419
A52: 295-300 | AS52: 3609857.1 | AU52: 3740456.8 | AX52: 3877081 | BD52: 4158616.1 | BQ52: 4955750 | BS52: 4964853 | CB52: 5441690.6 | CE52: 5672275.9 | CR52: 36420580
A53: 300-305 | AA53: 2875607.4 | AM53: 3478636.5 | AV53: 3890572.1 | AX53: 4015540.5 | AY53: 4163468.5 | BB53: 4264638.7 | BF53: 4476540.7 | BQ53: 5007594.2 | BS53: 5190830.9 | CR53: 37363429
A54: 305-310 | AJ54: 3435318.9 | AL54: 3580954.1 | AN54: 3692367.4 | AP54: 3781697 | BA54: 8686622.6 | BF54: 4601938.1 | BG54: 4696935.6 | BV54: 5457750.7 | CG54: 6027523.5 | CQ54: 6968453 | CR54: 50929561
A55: 310-315 | AL55: 3643079.5 | AS55: 3999649.4 | BC55: 9158203.1 | BM55: 10249302 | CR55: 27050234
A56: 315-320 | BC56: 9395556.3 | BD56: 4739749.2 | BE56: 4822047.9 | BH56: 4972485.1 | BP56: 5335645.2 | BU56: 5635206.3 | BW56: 5764122.3 | CR56: 40664812
A57: 320-325 | AP57: 4190493.6 | AR57: 4325767.8 | AU57: 4478427.6 | BC57: 4823066.1 | BF57: 4942603.3 | BP57: 5514089.4 | BR57: 5645659.7 | CR57: 33920107
A58: 325-330 | AN58: 4194520.6 | AS58: 4419718.4 | AT58: 4508363.6 | AV58: 4680353 | AY58: 4706435 | BY58: 6117170.7 | CR58: 28626561
A59: 330-335 | AX59: 4870617.3 | BA59: 4972549.6 | BB59: 5054112.3 | BY59: 6346015.1 | CR59: 21243294
A60: 335-340 | AL60: 4347364.1 | AN60: 4560433.6 | AR60: 4661661.8 | CR60: 13569459
A61: 340-345 | AS61: 4965403.4 | AY61: 5238011.3 | BC61: 5500147.3 | BE61: 5490470.8 | BO61: 6118667.7 | BW61: 6460565.2 | CR61: 33773266
A62: 345-350 | AR62: 5043662.5 | AS62: 4996102.5 | BK62: 5938783.5 | CD62: 6920251.1 | CR62: 22898800
A63: 350-355 | CF63: 7168993.7 | CL63: 15117404 | CR63: 22286397
A64: 355-360 | AT64: 5397055.4 | BP64: 13038978 | CB64: 7091202.2 | CC64: 7203080.3 | CR64: 32730316
A65: 360-365 | BH65: 6314961.7 | BQ65: 6770528.3 | CC65: 7322811.5 | CG65: 7622037.5 | CR65: 28030339
A66: 365-370 | BH66: 6357030 | CR66: 6357030
A67: 375-380 | BV67: 7402580.7 | CR67: 7402580.7
A68: 380-385 | BA68: 6478664.4 | CR68: 6478664.4
A69: 385-390 | BK69: 7111469.6 | CA69: 7937389.6 | CR69: 15048859
A70: 390-395 | BM70: 7363025.6 | CO70: 8944275.6 | CR70: 16307301
A71: 395-400 | BQ71: 7739350 | BT71: 7845403.8 | CR71: 15584754
A72: 400-405 | AZ72: 7024585.5 | BY72: 8227926.3 | CK72: 8890229 | CR72: 24142741
A73: 405-410 | AR73: 6688397.3 | AZ73: 7120327.4 | CR73: 13808725
A74: 410-415 | BR74: 8229458.2 | BS74: 8149725.2 | CR74: 16379183
A75: 415-420 | BA75: 7416657.1 | CR75: 7416657.1
A76: 420-425 | BM76: 8271645.7 | CR76: 8271645.7
A77: 425-430 | CB77: 9197093.9 | CR77: 9197093.9
A78: 430-435 | BU78: 8872829 | BV78: 8976544.5 | CR78: 17849374
A79: 445-450 | CM79: 10349823 | CR79: 10349823
A80: 485-490 | CN80: 11538945 | CR80: 11538945
A81: 520-525 | BO81: 11102477 | CR81: 11102477
A82: Grand Total | B82: 0 | C82: 0 | D82: 0 | E82: 0 | F82: 0 | G82: 0 | H82: 0 | I82: 0 | J82: 0 | K82: 0 | L82: 0 | M82: 0 | N82: 0 | O82: 0 | P82: 0 | Q82: 0 | R82: 436144.17 | S82: 0 | T82: 523986.65 | U82: 179782.64 | V82: 103675.84 | W82: 0 | X82: 572454.78 | Y82: 501069.99 | Z82: 2450297.7 | AA82: 3940276.8 | AB82: 3714028.3 | AC82: 5343773.5 | AD82: 3436488 | AE82: 7468739.9 | AF82: 6185446.4 | AG82: 9987522.5 | AH82: 4472369 | AI82: 18461639 | AJ82: 17862809 | AK82: 18798963 | AL82: 29552922 | AM82: 27956329 | AN82: 41034170 | AO82: 29801985 | AP82: 28016065 | AQ82: 40631890 | AR82: 54256344 | AS82: 50303317 | AT82: 37979436 | AU82: 36005450 | AV82: 44814776 | AW82: 48167071 | AX82: 45378412 | AY82: 73652332 | AZ82: 41134970 | BA82: 56188558 | BB82: 50511093 | BC82: 74789727 | BD82: 53661944 | BE82: 42527534 | BF82: 42379578 | BG82: 62159076 | BH82: 51760963 | BI82: 26097371 | BJ82: 37534794 | BK82: 35235818 | BL82: 17873139 | BM82: 45715707 | BN82: 32944530 | BO82: 39945458 | BP82: 46421931 | BQ82: 36017798 | BR82: 34313787 | BS82: 33587770 | BT82: 26946432 | BU82: 32174865 | BV82: 36464413 | BW82: 24094952 | BX82: 8227491.3 | BY82: 49782827 | BZ82: 1878748.9 | CA82: 12703947 | CB82: 25980604 | CC82: 21382899 | CD82: 10321980 | CE82: 17814803 | CF82: 11386864 | CG82: 18077507 | CH82: 4213729.3 | CI82: 4774773.7 | CJ82: 5561048.1 | CK82: 12968552 | CL82: 19782466 | CM82: 16018534 | CN82: 11538945 | CO82: 8944275.6 | CP82: 5259129.3 | CQ82: 12586600 | CR82: 1.9516779e+09

Sheet Sheet1
A1: ='Basket Options'!Q5 -> NVDA | B1: ='Basket Options'!R5 -> MSFT | C1: ='Basket Options'!T5 -> Basket Call
A2: ='Basket Options'!Q6 -> 282.06245 | B2: ='Basket Options'!R6 -> 474.89584 | C2: ='Basket Options'!T6 -> 2908890.1
A3: ='Basket Options'!Q7 -> 150.31207 | B3: ='Basket Options'!R7 -> 447.90163 | C3: ='Basket Options'!T7 -> 0
A4: ='Basket Options'!Q8 -> 224.56292 | B4: ='Basket Options'!R8 -> 537.90184 | C4: ='Basket Options'!T8 -> 1952547.2
A5: ='Basket Options'!Q9 -> 280.62658 | B5: ='Basket Options'!R9 -> 465.39602 | C5: ='Basket Options'!T9 -> 2768939.3
A6: ='Basket Options'!Q10 -> 202.93608 | B6: ='Basket Options'!R10 -> 445.8051 | C6: ='Basket Options'!T10 -> 379085.64
A7: ='Basket Options'!Q11 -> 72.303107 | B7: ='Basket Options'!R11 -> 396.5557 | C7: ='Basket Options'!T11 -> 0
A8: ='Basket Options'!Q12 -> 205.23503 | B8: ='Basket Options'!R12 -> 448.95958 | C8: ='Basket Options'!T12 -> 476792.85
A9: ='Basket Options'!Q13 -> 185.57671 | B9: ='Basket Options'!R13 -> 463.07933 | C9: ='Basket Options'!T13 -> 72043.491
A10: ='Basket Options'!Q14 -> 262.71511 | B10: ='Basket Options'!R14 -> 598.8451 | C10: ='Basket Options'!T14 -> 3664117.9
A11: ='Basket Options'!Q15 -> 162.35526 | B11: ='Basket Options'!R15 -> 442.54463 | C11: ='Basket Options'!T15 -> 0
A12: ='Basket Options'!Q16 -> 193.21302 | B12: ='Basket Options'!R16 -> 466.77773 | C12: ='Basket Options'!T16 -> 325528.03
... A2002: ='Basket Options'!Q2006 -> 162.16278 | B2002: ='Basket Options'!R2006 -> 487.42599 | C2002: ='Basket Options'!T2006 -> 0
