Workbook

Sheet Bonds
A1: Issuer Name | B1: Issue Date | C1: Maturity | D1: Bid Price | E1: Ask Price | F1: Cpn | G1: Currency | H1: Clean price | I1: Days to Maturity | J1: Accrued Interest | K1: Next Coupon Date | L1: Previous Coupon Date | M1: Invoice Price | N1: Time(Years) | O1: Present Value
A2: United States Treasury Note/Bond | B2: 2/28/2018 | C2: 2/28/2025 | D2: 99.980469 | E2: 100.00781 | F2: 2.75 | G2: USD | H2: =(D2+E2)/2 -> 99.994141 | I2: =DAYS(C2,Context!$C$19) -> 4 | J2: =ACCRINT(L2,K2,Context!$C$19,F2/100,100,2,1) -> 1.3451087 | K2: =COUPNCD(Context!$C$19,C2,2,1) -> 45716 | L2: =COUPPCD(Context!$C$19,C2,2,1) -> 45532 | M2: =H2+J2 -> 101.33925 | N2: =(C2-Context!$C$19)/365.25 -> 0.010951403
A3: United States Treasury Note/Bond | B3: 2/28/2023 | C3: 2/28/2025 | D3: 99.984375 | E3: 100.01953 | F3: 4.625 | G3: USD | H3: =(D3+E3)/2 -> 100.00195 | I3: =DAYS(C3,Context!$C$19) -> 4 | J3: =ACCRINT(L3,K3,Context!$C$19,F3/100,100,2,1) -> 2.2622283 | K3: =COUPNCD(Context!$C$19,C3,2,1) -> 45716 | L3: =COUPPCD(Context!$C$19,C3,2,1) -> 45532 | M3: =H3+J3 -> 102.26418 | N3: =(C3-Context!$C$19)/365.25 -> 0.010951403
A4: United States Treasury Note/Bond | B4: 3/2/2020 | C4: 2/28/2025 | D4: 99.945312 | E4: 100.01172 | F4: 1.125 | G4: USD | H4: =(D4+E4)/2 -> 99.978516 | I4: =DAYS(C4,Context!$C$19) -> 4 | J4: =ACCRINT(L4,K4,Context!$C$19,F4/100,100,2,1) -> 0.55027174 | K4: =COUPNCD(Context!$C$19,C4,2,1) -> 45716 | L4: =COUPPCD(Context!$C$19,C4,2,1) -> 45532 | M4: =H4+J4 -> 100.52879 | N4: =(C4-Context!$C$19)/365.25 -> 0.010951403
A5: United States Treasury Note/Bond | B5: 3/15/2022 | C5: 3/15/2025 | D5: 99.859375 | E5: 99.914062 | F5: 1.75 | G5: USD | H5: =(D5+E5)/2 -> 99.886719 | I5: =DAYS(C5,Context!$C$19) -> 19 | J5: =ACCRINT(L5,K5,Context!$C$19,F5/100,100,2,1) -> 0.78314917 | K5: =COUPNCD(Context!$C$19,C5,2,1) -> 45731 | L5: =COUPPCD(Context!$C$19,C5,2,1) -> 45550 | M5: =H5+J5 -> 100.66987 | N5: =(C5-Context!$C$19)/365.25 -> 0.052019165
A6: United States Treasury Note/Bond | B6: 3/31/2020 | C6: 3/31/2025 | D6: 99.621094 | E6: 99.703125 | F6: 0.5 | G6: USD | H6: =(D6+E6)/2 -> 99.662109 | I6: =DAYS(C6,Context!$C$19) -> 35 | J6: =ACCRINT(L6,K6,Context!$C$19,F6/100,100,2,1) -> 0.20192308 | K6: =COUPNCD(Context!$C$19,C6,2,1) -> 45747 | L6: =COUPPCD(Context!$C$19,C6,2,1) -> 45565 | M6: =H6+J6 -> 99.864032 | N6: =(C6-Context!$C$19)/365.25 -> 0.095824778
A7: United States Treasury Note/Bond | B7: 3/31/2023 | C7: 3/31/2025 | D7: 99.9375 | E7: 99.992188 | F7: 3.875 | G7: USD | H7: =(D7+E7)/2 -> 99.964844 | I7: =DAYS(C7,Context!$C$19) -> 35 | J7: =ACCRINT(L7,K7,Context!$C$19,F7/100,100,2,1) -> 1.5649038 | K7: =COUPNCD(Context!$C$19,C7,2,1) -> 45747 | L7: =COUPPCD(Context!$C$19,C7,2,1) -> 45565 | M7: =H7+J7 -> 101.52975 | N7: =(C7-Context!$C$19)/365.25 -> 0.095824778
A8: United States Treasury Note/Bond | B8: 4/2/2018 | C8: 3/31/2025 | D8: 99.820312 | E8: 99.886719 | F8: 2.625 | G8: USD | H8: =(D8+E8)/2 -> 99.853516 | I8: =DAYS(C8,Context!$C$19) -> 35 | J8: =ACCRINT(L8,K8,Context!$C$19,F8/100,100,2,1) -> 1.0600962 | K8: =COUPNCD(Context!$C$19,C8,2,1) -> 45747 | L8: =COUPPCD(Context!$C$19,C8,2,1) -> 45565 | M8: =H8+J8 -> 100.91361 | N8: =(C8-Context!$C$19)/365.25 -> 0.095824778
A9: United States Treasury Note/Bond | B9: 4/18/2022 | C9: 4/15/2025 | D9: 99.746094 | E9: 99.835938 | F9: 2.625 | G9: USD | H9: =(D9+E9)/2 -> 99.791016 | I9: =DAYS(C9,Context!$C$19) -> 50 | J9: =ACCRINT(L9,K9,Context!$C$19,F9/100,100,2,1) -> 0.95192308 | K9: =COUPNCD(Context!$C$19,C9,2,1) -> 45762 | L9: =COUPPCD(Context!$C$19,C9,2,1) -> 45580 | M9: =H9+J9 -> 100.74294 | N9: =(C9-Context!$C$19)/365.25 -> 0.13689254
A10: United States Treasury Note/Bond | B10: 4/30/2018 | C10: 4/30/2025 | D10: 99.730469 | E10: 99.792969 | F10: 2.875 | G10: USD | H10: =(D10+E10)/2 -> 99.761719 | I10: =DAYS(C10,Context!$C$19) -> 65 | J10: =ACCRINT(L10,K10,Context!$C$19,F10/100,100,2,1) -> 0.92410714 | K10: =COUPNCD(Context!$C$19,C10,2,1) -> 45777 | L10: =COUPPCD(Context!$C$19,C10,2,1) -> 45595 | M10: =H10+J10 -> 100.68583 | N10: =(C10-Context!$C$19)/365.25 -> 0.1779603
A11: United States Treasury Note/Bond | B11: 4/30/2020 | C11: 4/30/2025 | D11: 99.273438 | E11: 99.367188 | F11: 0.375 | G11: USD | H11: =(D11+E11)/2 -> 99.320312 | I11: =DAYS(C11,Context!$C$19) -> 65 | J11: =ACCRINT(L11,K11,Context!$C$19,F11/100,100,2,1) -> 0.12053571 | K11: =COUPNCD(Context!$C$19,C11,2,1) -> 45777 | L11: =COUPPCD(Context!$C$19,C11,2,1) -> 45595 | M11: =H11+J11 -> 99.440848 | N11: =(C11-Context!$C$19)/365.25 -> 0.1779603
A12: United States Treasury Note/Bond | B12: 5/1/2023 | C12: 4/30/2025 | D12: 99.90625 | E12: 99.945312 | F12: 3.875 | G12: USD | H12: =(D12+E12)/2 -> 99.925781 | I12: =DAYS(C12,Context!$C$19) -> 65 | J12: =ACCRINT(L12,K12,Context!$C$19,F12/100,100,2,1) -> 1.2455357 | K12: =COUPNCD(Context!$C$19,C12,2,1) -> 45777 | L12: =COUPPCD(Context!$C$19,C12,2,1) -> 45595 | M12: =H12+J12 -> 101.17132 | N12: =(C12-Context!$C$19)/365.25 -> 0.1779603
A13: United States Treasury Note/Bond | B13: 5/15/2015 | C13: 5/15/2025 | D13: 99.515625 | E13: 99.582031 | F13: 2.125 | G13: USD | H13: =(D13+E13)/2 -> 99.548828 | I13: =DAYS(C13,Context!$C$19) -> 80 | J13: =ACCRINT(L13,K13,Context!$C$19,F13/100,100,2,1) -> 0.59288674 | K13: =COUPNCD(Context!$C$19,C13,2,1) -> 45792 | L13: =COUPPCD(Context!$C$19,C13,2,1) -> 45611 | M13: =H13+J13 -> 100.14171 | N13: =(C13-Context!$C$19)/365.25 -> 0.21902806
... A348: United States Treasury Note/Bond | B348: 2/18/2025 | C348: 2/15/2055 | D348: 99.765625 | E348: 99.796875 | F348: 4.625 | G348: USD | H348: =(D348+E348)/2 -> 99.78125 | I348: =DAYS(C348,Context!$C$19) -> 10948 | J348: =ACCRINT(L348,K348,Context!$C$19,F348/100,100,2,1) -> 0.11498619 | K348: =COUPNCD(Context!$C$19,C348,2,1) -> 45884 | L348: =COUPPCD(Context!$C$19,C348,2,1) -> 45703 | M348: =H348+J348 -> 99.896236 | N348: =(C348-Context!$C$19)/365.25 -> 29.97399

Sheet Parameter
A1: Parameters | B1: Value
A2: a | B2: 0.01
A3: b | B3: 0.01
A4: c | B4: 0.01
A5: d | B5: 0.01
A6: f | B6: 0.01
A7: g | B7: 0.01
A8: h | B8: 0.01
A9: Valuation Date | B9: 45712
A10: r(t) | B10: =B2 + B3* 𝑡 +B4 * 𝑡^2 +B5 * 𝑒 ^(B6* 𝑡) +B7 * ln(𝑡 − B8) -> #ERROR!

Sheet Context
A1: Summary
A2: SRCH Results
A4: Number of securities: 347
A5: Currency: USD
A8: Created by NEEL SHAH ( NEW YORK UNIVERSITY ABU DHABI ) on 02/24/2025 21:03:45 GMT-0500 (EST)
A10: SRCH Criteria
A11: Asset Classes: Corporates, Governments
A12: Sources: All Securities
A13: Security:
A14: AND | B14: Security Status | C14: Include | D14: Bonds : Active
A15: AND | B15: Issuer Name | C15: Include | D15: United States Treasury Note/Bond ( T ) ( current and subs )
A16: AND | B16: Country/Region of Risk | C16: Include | D16: United States of America
C19: 45712
